{
  "ang": 961,
  "line_count": 47,
  "lines": [
    {
      "index": 1,
      "verse_id": 41060,
      "shabad_num": 0,
      "shabad_id": null,
      "gurmukhi": "ਅੰਮ੍ਰਿਤ ਬਾਣੀ ਸਤਿਗੁਰ ਪੂਰੇ ਕੀ ਜਿਸੁ ਕਿਰਪਾਲੁ ਹੋਵੈ ਤਿਸੁ ਰਿਦੈ ਵਸੇਹਾ ॥",
      "site_roman": "",
      "sahib_singh_pa": "",
      "roman": "amrit bāṇī satigur pūrē kī jis kirpāl hovē tis ridē vasēhā",
      "translation_ru": "Амритная Бани совершенного Сатгуру поселяется в сердце того, к кому Господь милостив."
    },
    {
      "index": 2,
      "verse_id": 41061,
      "shabad_num": 0,
      "shabad_id": null,
      "gurmukhi": "ਆਵਣ ਜਾਣਾ ਤਿਸ ਕਾ ਕਟੀਐ ਸਦਾ ਸਦਾ ਸੁਖੁ ਹੋਹਾ ॥੨॥",
      "site_roman": "",
      "sahib_singh_pa": "",
      "roman": "āvaṇ jāṇā tis kā kaṭīai sadā sadā sukh hohā",
      "translation_ru": "Его круг приходов и уходов пресекается, и он навсегда обретает покой."
    },
    {
      "index": 3,
      "verse_id": 41062,
      "shabad_num": 0,
      "shabad_id": null,
      "gurmukhi": "ਪਉੜੀ ॥",
      "site_roman": "",
      "sahib_singh_pa": "",
      "roman": "pauṛī",
      "translation_ru": "Паури."
    },
    {
      "index": 4,
      "verse_id": 41063,
      "shabad_num": 0,
      "shabad_id": null,
      "gurmukhi": "ਜੋ ਤੁਧੁ ਭਾਣਾ ਜੰਤੁ ਸੋ ਤੁਧੁ ਬੁਝਈ ॥",
      "site_roman": "",
      "sahib_singh_pa": "",
      "roman": "jo tudh bhāṇā jant so tudh bujhī",
      "translation_ru": "О Господь! То существо, которое становится Тебе дорогим, входит с Тобой в связь и познаёт Тебя."
    },
    {
      "index": 5,
      "verse_id": 41064,
      "shabad_num": 0,
      "shabad_id": null,
      "gurmukhi": "ਜੋ ਤੁਧੁ ਭਾਣਾ ਜੰਤੁ ਸੁ ਦਰਗਹ ਸਿਝਈ ॥",
      "site_roman": "",
      "sahib_singh_pa": "",
      "roman": "jo tudh bhāṇā jant so dargah sijhī",
      "translation_ru": "То существо, которое становится Тебе дорогим, успешно завершает путь жизни и достигает Твоего присутствия."
    },
    {
      "index": 6,
      "verse_id": 41065,
      "shabad_num": 0,
      "shabad_id": null,
      "gurmukhi": "ਜਿਸ ਨੋ ਤੇਰੀ ਨਦਰਿ ਹਉਮੈ ਤਿਸੁ ਗਈ ॥",
      "site_roman": "",
      "sahib_singh_pa": "",
      "roman": "jis no terī nadar haumē tis gaī",
      "translation_ru": "На кого падает Твой милостивый взгляд, у того исчезает Хоумэ, чувство собственного «я»."
    },
    {
      "index": 7,
      "verse_id": 41066,
      "shabad_num": 0,
      "shabad_id": null,
      "gurmukhi": "ਜਿਸ ਨੋ ਤੂ ਸੰਤੁਸਟੁ ਕਲਮਲ ਤਿਸੁ ਖਈ ॥",
      "site_roman": "",
      "sahib_singh_pa": "",
      "roman": "jis no tū santusṭ kalmal tis khaī",
      "translation_ru": "Кем Ты доволен, у того уничтожаются все грехи."
    },
    {
      "index": 8,
      "verse_id": 41067,
      "shabad_num": 0,
      "shabad_id": null,
      "gurmukhi": "ਜਿਸ ਕੈ ਸੁਆਮੀ ਵਲਿ ਨਿਰਭਉ ਸੋ ਭਈ ॥",
      "site_roman": "",
      "sahib_singh_pa": "",
      "roman": "jis kē suāmī val nirbhau so bhaī",
      "translation_ru": "Человек, на чьей стороне Владыка-Господь, становится бесстрашным перед страхами мира."
    },
    {
      "index": 9,
      "verse_id": 41068,
      "shabad_num": 0,
      "shabad_id": null,
      "gurmukhi": "ਜਿਸ ਨੋ ਤੂ ਕਿਰਪਾਲੁ ਸਚਾ ਸੋ ਥਿਅਈ ॥",
      "site_roman": "",
      "sahib_singh_pa": "",
      "roman": "jis no tū kirpāl sachā so thiāī",
      "translation_ru": "О Господь! К кому Ты милостив, тот становится устойчивым и непоколебимым перед нападениями майи."
    },
    {
      "index": 10,
      "verse_id": 41069,
      "shabad_num": 0,
      "shabad_id": null,
      "gurmukhi": "ਜਿਸ ਨੋ ਤੇਰੀ ਮਇਆ ਨ ਪੋਹੈ ਅਗਨਈ ॥",
      "site_roman": "",
      "sahib_singh_pa": "",
      "roman": "jis no terī mēā na pohē agnaī",
      "translation_ru": "Того, на кого есть Твоя милость, не может коснуться огонь майи."
    },
    {
      "index": 11,
      "verse_id": 41070,
      "shabad_num": 0,
      "shabad_id": null,
      "gurmukhi": "ਤਿਸ ਨੋ ਸਦਾ ਦਇਆਲੁ ਜਿਨਿ ਗੁਰ ਤੇ ਮਤਿ ਲਈ ॥੭॥",
      "site_roman": "",
      "sahib_singh_pa": "",
      "roman": "tis no sadā daiāl jin gur tē mat laī",
      "translation_ru": "Но, о Господь, Ты всегда милостив к тому, кто научился у Гуру мудрости человеческой жизни."
    },
    {
      "index": 12,
      "verse_id": 41071,
      "shabad_num": 0,
      "shabad_id": null,
      "gurmukhi": "ਸਲੋਕ ਮਃ ੫ ॥",
      "site_roman": "",
      "sahib_singh_pa": "",
      "roman": "salok mahallā panjvāṅ",
      "translation_ru": "Шлок, пятый Махала."
    },
    {
      "index": 13,
      "verse_id": 41072,
      "shabad_num": 0,
      "shabad_id": null,
      "gurmukhi": "ਕਰਿ ਕਿਰਪਾ ਕਿਰਪਾਲ ਆਪੇ ਬਖਸਿ ਲੈ ॥",
      "site_roman": "",
      "sahib_singh_pa": "",
      "roman": "kar kirpā kirpāl āpē bakhas lē",
      "translation_ru": "О Милостивый Господь! Прояви милость и Сам прости меня."
    },
    {
      "index": 14,
      "verse_id": 41073,
      "shabad_num": 0,
      "shabad_id": null,
      "gurmukhi": "ਸਦਾ ਸਦਾ ਜਪੀ ਤੇਰਾ ਨਾਮੁ ਸਤਿਗੁਰ ਪਾਇ ਪੈ ॥",
      "site_roman": "",
      "sahib_singh_pa": "",
      "roman": "sadā sadā japī terā nām satigur pāi pē",
      "translation_ru": "Пусть, припав к стопам Сатгуру, я всегда-всегда повторяю Твоё Имя."
    },
    {
      "index": 15,
      "verse_id": 41074,
      "shabad_num": 0,
      "shabad_id": null,
      "gurmukhi": "ਮਨ ਤਨ ਅੰਤਰਿ ਵਸੁ ਦੂਖਾ ਨਾਸੁ ਹੋਇ ॥",
      "site_roman": "",
      "sahib_singh_pa": "",
      "roman": "man tan antar vas dūkhā nās hoi",
      "translation_ru": "О Милостивый! Поселись в моём уме и теле, чтобы мои страдания исчезли."
    },
    {
      "index": 16,
      "verse_id": 41075,
      "shabad_num": 0,
      "shabad_id": null,
      "gurmukhi": "ਹਥ ਦੇਇ ਆਪਿ ਰਖੁ ਵਿਆਪੈ ਭਉ ਨ ਕੋਇ ॥",
      "site_roman": "",
      "sahib_singh_pa": "",
      "roman": "hath dē āp rakh viāpē bhau na koi",
      "translation_ru": "Сам защити меня, протянув Свою руку, чтобы никакой страх не мог овладеть мной."
    },
    {
      "index": 17,
      "verse_id": 41076,
      "shabad_num": 0,
      "shabad_id": null,
      "gurmukhi": "ਗੁਣ ਗਾਵਾ ਦਿਨੁ ਰੈਣਿ ਏਤੈ ਕੰਮਿ ਲਾਇ ॥",
      "site_roman": "",
      "sahib_singh_pa": "",
      "roman": "guṇ gāvā din rēṇ etē kamm lāi",
      "translation_ru": "О Милостивый! Держи меня занятым этим делом, чтобы я днём и ночью воспевал Твои качества."
    },
    {
      "index": 18,
      "verse_id": 41077,
      "shabad_num": 0,
      "shabad_id": null,
      "gurmukhi": "ਸੰਤ ਜਨਾ ਕੈ ਸੰਗਿ ਹਉਮੈ ਰੋਗੁ ਜਾਇ ॥",
      "site_roman": "",
      "sahib_singh_pa": "",
      "roman": "sant janā kē saṅg haumē rog jāi",
      "translation_ru": "Пусть в обществе святых людей будет отсечена болезнь моего Хоумэ."
    },
    {
      "index": 19,
      "verse_id": 41078,
      "shabad_num": 0,
      "shabad_id": null,
      "gurmukhi": "ਸਰਬ ਨਿਰੰਤਰਿ ਖਸਮੁ ਏਕੋ ਰਵਿ ਰਹਿਆ ॥",
      "site_roman": "",
      "sahib_singh_pa": "",
      "roman": "sarab niraṅtar khasam ēko rav rahiā",
      "translation_ru": "О брат! Один Господь-Владыка непрерывно пребывает во всех существах."
    },
    {
      "index": 20,
      "verse_id": 41079,
      "shabad_num": 0,
      "shabad_id": null,
      "gurmukhi": "ਗੁਰ ਪਰਸਾਦੀ ਸਚੁ ਸਚੋ ਸਚੁ ਲਹਿਆ ॥",
      "site_roman": "",
      "sahib_singh_pa": "",
      "roman": "gur prasādī sach sacho sach lahiā",
      "translation_ru": "Но вечного, истиннейшего Господа находят только по милости Гуру."
    },
    {
      "index": 21,
      "verse_id": 41080,
      "shabad_num": 0,
      "shabad_id": null,
      "gurmukhi": "ਦਇਆ ਕਰਹੁ ਦਇਆਲ ਅਪਣੀ ਸਿਫਤਿ ਦੇਹੁ ॥",
      "site_roman": "",
      "sahib_singh_pa": "",
      "roman": "daiā karah daiāl apṇī sifat dēh",
      "translation_ru": "О милостивый Господь! Прояви милость, даруй мне Твоё восхваление."
    },
    {
      "index": 22,
      "verse_id": 41081,
      "shabad_num": 0,
      "shabad_id": null,
      "gurmukhi": "ਦਰਸਨੁ ਦੇਖਿ ਨਿਹਾਲ ਨਾਨਕ ਪ੍ਰੀਤਿ ਏਹ ॥੧॥",
      "site_roman": "",
      "sahib_singh_pa": "",
      "roman": "darsan dēkh nihāl nānak prīt eh",
      "translation_ru": "У Нанака есть лишь это стремление: созерцая Твоё явление, пребывать в радости."
    },
    {
      "index": 23,
      "verse_id": 41082,
      "shabad_num": 0,
      "shabad_id": null,
      "gurmukhi": "ਮਃ ੫ ॥",
      "site_roman": "",
      "sahib_singh_pa": "",
      "roman": "mahallā panjvāṅ",
      "translation_ru": "Пятый Махала."
    },
    {
      "index": 24,
      "verse_id": 41083,
      "shabad_num": 0,
      "shabad_id": null,
      "gurmukhi": "ਏਕੋ ਜਪੀਐ ਮਨੈ ਮਾਹਿ ਇਕਸ ਕੀ ਸਰਣਾਇ ॥",
      "site_roman": "",
      "sahib_singh_pa": "",
      "roman": "ēko japīē manē māh ikas kī saraṇāi",
      "translation_ru": "Одного Господа следует созерцать в уме, прибежище следует принимать только у одного Господа."
    },
    {
      "index": 25,
      "verse_id": 41084,
      "shabad_num": 0,
      "shabad_id": null,
      "gurmukhi": "ਇਕਸੁ ਸਿਉ ਕਰਿ ਪਿਰਹੜੀ ਦੂਜੀ ਨਾਹੀ ਜਾਇ ॥",
      "site_roman": "",
      "sahib_singh_pa": "",
      "roman": "ikas sio kar pirhaṛī dūjī nāhī jāi",
      "translation_ru": "О ум! Люби только одного Господа; кроме Него нет иного места опоры."
    },
    {
      "index": 26,
      "verse_id": 41085,
      "shabad_num": 0,
      "shabad_id": null,
      "gurmukhi": "ਇਕੋ ਦਾਤਾ ਮੰਗੀਐ ਸਭੁ ਕਿਛੁ ਪਲੈ ਪਾਇ ॥",
      "site_roman": "",
      "sahib_singh_pa": "",
      "roman": "iko dātā maṅgīē sabh kichh palē pāi",
      "translation_ru": "Просить следует только у одного Господа-Даятеля, ибо всё получается только от Него."
    },
    {
      "index": 27,
      "verse_id": 41086,
      "shabad_num": 0,
      "shabad_id": null,
      "gurmukhi": "ਮਨਿ ਤਨਿ ਸਾਸਿ ਗਿਰਾਸਿ ਪ੍ਰਭੁ ਇਕੋ ਇਕੁ ਧਿਆਇ ॥",
      "site_roman": "",
      "sahib_singh_pa": "",
      "roman": "man tan sās girās prabh iko ik dhiāi",
      "translation_ru": "О брат! Умом, телом, с каждым дыханием и с каждым куском пищи поминай одного-единственного Господа."
    },
    {
      "index": 28,
      "verse_id": 41087,
      "shabad_num": 0,
      "shabad_id": null,
      "gurmukhi": "ਅੰਮ੍ਰਿਤੁ ਨਾਮੁ ਨਿਧਾਨੁ ਸਚੁ ਗੁਰਮੁਖਿ ਪਾਇਆ ਜਾਇ ॥",
      "site_roman": "",
      "sahib_singh_pa": "",
      "roman": "amrit nām nidhān sach gurmukh pāiā jāi",
      "translation_ru": "Дающее духовную жизнь Имя Господа, вечное сокровище, обретается только через Гуру."
    },
    {
      "index": 29,
      "verse_id": 41088,
      "shabad_num": 0,
      "shabad_id": null,
      "gurmukhi": "ਵਡਭਾਗੀ ਤੇ ਸੰਤ ਜਨ ਜਿਨ ਮਨਿ ਵੁਠਾ ਆਇ ॥",
      "site_roman": "",
      "sahib_singh_pa": "",
      "roman": "vaḍbhāgī tē sant jan jin man vuṭhā āi",
      "translation_ru": "Великим счастьем обладают те святые люди, в чьих сердцах поселился Господь."
    },
    {
      "index": 30,
      "verse_id": 41089,
      "shabad_num": 0,
      "shabad_id": null,
      "gurmukhi": "ਜਲਿ ਥਲਿ ਮਹੀਅਲਿ ਰਵਿ ਰਹਿਆ ਦੂਜਾ ਕੋਈ ਨਾਹਿ ॥",
      "site_roman": "",
      "sahib_singh_pa": "",
      "roman": "jal thal mahīal rav rahiā dūjā koī nāh",
      "translation_ru": "Господь пребывает в воде, на земле и в небесном пространстве; кроме Него нигде нет никого другого."
    },
    {
      "index": 31,
      "verse_id": 41090,
      "shabad_num": 0,
      "shabad_id": null,
      "gurmukhi": "ਨਾਮੁ ਧਿਆਈ ਨਾਮੁ ਉਚਰਾ ਨਾਨਕ ਖਸਮ ਰਜਾਇ ॥੨॥",
      "site_roman": "",
      "sahib_singh_pa": "",
      "roman": "nām dhiāī nām ucharā nānak khasam rajāi",
      "translation_ru": "О Нанак! Молись, чтобы и я созерцал Имя Господа, произносил Имя устами и жил в воле Господа-Владыки."
    },
    {
      "index": 32,
      "verse_id": 41091,
      "shabad_num": 0,
      "shabad_id": null,
      "gurmukhi": "ਪਉੜੀ ॥",
      "site_roman": "",
      "sahib_singh_pa": "",
      "roman": "pauṛī",
      "translation_ru": "Паури."
    },
    {
      "index": 33,
      "verse_id": 41092,
      "shabad_num": 0,
      "shabad_id": null,
      "gurmukhi": "ਜਿਸ ਨੋ ਤੂ ਰਖਵਾਲਾ ਮਾਰੇ ਤਿਸੁ ਕਉਣੁ ॥",
      "site_roman": "",
      "sahib_singh_pa": "",
      "roman": "jis no tū rakhvālā mārē tis kauṇ",
      "translation_ru": "О Господь! Человека, которому Ты стал Защитником, никто, никакой порок, не может убить."
    },
    {
      "index": 34,
      "verse_id": 41093,
      "shabad_num": 0,
      "shabad_id": null,
      "gurmukhi": "ਜਿਸ ਨੋ ਤੂ ਰਖਵਾਲਾ ਜਿਤਾ ਤਿਨੈ ਭੈਣੁ ॥",
      "site_roman": "",
      "sahib_singh_pa": "",
      "roman": "jis no tū rakhvālā jitā tinē bhēṇ",
      "translation_ru": "Потому что тот, кому Ты Защитник, уже победил весь мир."
    },
    {
      "index": 35,
      "verse_id": 41094,
      "shabad_num": 0,
      "shabad_id": null,
      "gurmukhi": "ਜਿਸ ਨੋ ਤੇਰਾ ਅੰਗੁ ਤਿਸੁ ਮੁਖੁ ਉਜਲਾ ॥",
      "site_roman": "",
      "sahib_singh_pa": "",
      "roman": "jis no terā aṅg tis mukh ujlā",
      "translation_ru": "О Господь! Тот, кто получил Твою опору, стал просветлённым и достойным в человеческой ответственности."
    },
    {
      "index": 36,
      "verse_id": 41095,
      "shabad_num": 0,
      "shabad_id": null,
      "gurmukhi": "ਜਿਸ ਨੋ ਤੇਰਾ ਅੰਗੁ ਸੁ ਨਿਰਮਲੀ ਹੂੰ ਨਿਰਮਲਾ ॥",
      "site_roman": "",
      "sahib_singh_pa": "",
      "roman": "jis no terā aṅg so nirmalī hūṅ nirmalā",
      "translation_ru": "Тот, кто имеет Твою опору, становится чище самых чистых, человеком святой жизни."
    },
    {
      "index": 37,
      "verse_id": 41096,
      "shabad_num": 0,
      "shabad_id": null,
      "gurmukhi": "ਜਿਸ ਨੋ ਤੇਰੀ ਨਦਰਿ ਨ ਲੇਖਾ ਪੁਛੀਐ ॥",
      "site_roman": "",
      "sahib_singh_pa": "",
      "roman": "jis no terī nadar na lekhā puchhīai",
      "translation_ru": "О Господь! С того, кому достался Твой милостивый взгляд, не спрашивают счёта дел, совершённых в жизни."
    },
    {
      "index": 38,
      "verse_id": 41097,
      "shabad_num": 0,
      "shabad_id": null,
      "gurmukhi": "ਜਿਸ ਨੋ ਤੇਰੀ ਖੁਸੀ ਤਿਨਿ ਨਉ ਨਿਧਿ ਭੁੰਚੀਐ ॥",
      "site_roman": "",
      "sahib_singh_pa": "",
      "roman": "jis no terī khushī tin nau nidh bhuñchīai",
      "translation_ru": "Ибо тот, кто получил Твоё благоволение, уже насладился девятью сокровищами в виде Твоего Имени."
    },
    {
      "index": 39,
      "verse_id": 41098,
      "shabad_num": 0,
      "shabad_id": null,
      "gurmukhi": "ਜਿਸ ਨੋ ਤੂ ਪ੍ਰਭ ਵਲਿ ਤਿਸੁ ਕਿਆ ਮੁਹਛੰਦਗੀ ॥",
      "site_roman": "",
      "sahib_singh_pa": "",
      "roman": "jis no tū prabh val tis kiā muhchhandagī",
      "translation_ru": "О Господь! Тот, на чьей стороне Ты, не остаётся зависимым ни от кого."
    },
    {
      "index": 40,
      "verse_id": 41099,
      "shabad_num": 0,
      "shabad_id": null,
      "gurmukhi": "ਜਿਸ ਨੋ ਤੇਰੀ ਮਿਹਰ ਸੁ ਤੇਰੀ ਬੰਦਿਗੀ ॥੮॥",
      "site_roman": "",
      "sahib_singh_pa": "",
      "roman": "jis no terī mihar so terī bandigī",
      "translation_ru": "Тот, на ком Твоя милость, совершает Твоё поклонение и служение."
    },
    {
      "index": 41,
      "verse_id": 41100,
      "shabad_num": 0,
      "shabad_id": null,
      "gurmukhi": "ਸਲੋਕ ਮਹਲਾ ੫ ॥",
      "site_roman": "",
      "sahib_singh_pa": "",
      "roman": "salok mahallā panjvāṅ",
      "translation_ru": "Шлок, пятый Махала."
    },
    {
      "index": 42,
      "verse_id": 41101,
      "shabad_num": 0,
      "shabad_id": null,
      "gurmukhi": "ਹੋਹੁ ਕ੍ਰਿਪਾਲ ਸੁਆਮੀ ਮੇਰੇ ਸੰਤਾਂ ਸੰਗਿ ਵਿਹਾਵੇ ॥",
      "site_roman": "",
      "sahib_singh_pa": "",
      "roman": "hoh kripāl suāmī merē santāṅ saṅg vihāvē",
      "translation_ru": "О мой Владыка! Будь милостив ко мне, чтобы моя жизнь проходила в обществе святых."
    },
    {
      "index": 43,
      "verse_id": 41102,
      "shabad_num": 0,
      "shabad_id": null,
      "gurmukhi": "ਤੁਧਹੁ ਭੁਲੇ ਸਿ ਜਮਿ ਜਮਿ ਮਰਦੇ ਤਿਨ ਕਦੇ ਨ ਚੁਕਨਿ ਹਾਵੇ ॥੧॥",
      "site_roman": "",
      "sahib_singh_pa": "",
      "roman": "tudhah bhulē se jam jam mardē tin kadē na chukan hāvē",
      "translation_ru": "Те люди, которые отпадают от Тебя, снова и снова рождаются и умирают; их стоны никогда не прекращаются."
    },
    {
      "index": 44,
      "verse_id": 41103,
      "shabad_num": 0,
      "shabad_id": null,
      "gurmukhi": "ਮਃ ੫ ॥",
      "site_roman": "",
      "sahib_singh_pa": "",
      "roman": "mahallā panjvāṅ",
      "translation_ru": "Пятый Махала."
    },
    {
      "index": 45,
      "verse_id": 41104,
      "shabad_num": 0,
      "shabad_id": null,
      "gurmukhi": "ਸਤਿਗੁਰੁ ਸਿਮਰਹੁ ਆਪਣਾ ਘਟਿ ਅਵਘਟਿ ਘਟ ਘਾਟ ॥",
      "site_roman": "",
      "sahib_singh_pa": "",
      "roman": "satigur simrah āpṇā ghaṭ avghaṭ ghaṭ ghāṭ",
      "translation_ru": "О брат! Помните своего Гуру в сердце, вставая и садясь, во всякое время и в любом месте."
    },
    {
      "index": 46,
      "verse_id": 41105,
      "shabad_num": 0,
      "shabad_id": null,
      "gurmukhi": "ਹਰਿ ਹਰਿ ਨਾਮੁ ਜਪੰਤਿਆ ਕੋਇ ਨ ਬੰਧੈ ਵਾਟ ॥੨॥",
      "site_roman": "",
      "sahib_singh_pa": "",
      "roman": "har har nām japantiā koi na bandhē vāṭ",
      "translation_ru": "Когда повторяют Имя Хар-Хар, никакой порок не может преградить путь жизни."
    },
    {
      "index": 47,
      "verse_id": 41106,
      "shabad_num": 0,
      "shabad_id": null,
      "gurmukhi": "ਪਉੜੀ ॥",
      "site_roman": "",
      "sahib_singh_pa": "",
      "roman": "pauṛī",
      "translation_ru": "Паури."
    }
  ]
}
