{
  "ang": 211,
  "lines": [
    {
      "verse_id": 9028,
      "gurmukhi": "ਪ੍ਰਭ ਕੇ ਚਾਕਰ ਸੇ ਭਲੇ ॥",
      "roman": "prabh ke chākar se bhale ॥",
      "sahib_singh_pa": "(ਜੇਹੜੇ ਮਨੁੱਖ) ਪਰਮਾਤਮਾ ਦੇ ਸੇਵਕ ਬਣਦੇ ਹਨ,",
      "translation_ru": "Те люди, которые становятся слугами Бога,"
    },
    {
      "verse_id": 9029,
      "gurmukhi": "ਨਾਨਕ ਤਿਨ ਮੁਖ ਊਜਲੇ ॥੪॥੩॥੧੪੧॥",
      "roman": "nānak tin mukh ūjle ॥4॥3॥141॥",
      "sahib_singh_pa": "ਹੇ ਨਾਨਕ! (ਆਖ-) ਉਹ ਭਾਗਾਂ ਵਾਲੇ ਹੋ ਜਾਂਦੇ ਹਨ (ਪਰਮਾਤਮਾ ਦੇ ਦਰਬਾਰ ਵਿਚ) ਉਹਨਾਂ ਦੇ ਮੂੰਹ ਰੋਸ਼ਨ ਹੁੰਦੇ ਹਨ ॥੪॥੩॥੧੪੧॥",
      "translation_ru": "о Нанак, становятся благословенными; в Божьем дворе их лица сияют. ॥4॥3॥141॥"
    },
    {
      "verse_id": 9030,
      "gurmukhi": "ਗਉੜੀ ਮਹਲਾ ੫ ॥",
      "roman": "Gauṛī mahalā 5",
      "sahib_singh_pa": "None",
      "translation_ru": ""
    },
    {
      "verse_id": 9031,
      "gurmukhi": "ਜੀਅਰੇ ਓਲੑਾ ਨਾਮ ਕਾ ॥",
      "roman": "Jīare olhā nām kā",
      "sahib_singh_pa": "ਹੇ ਮੇਰੀ ਜਿੰਦੇ! ਪਰਮਾਤਮਾ ਦੇ ਨਾਮ ਦਾ (ਹੀ) ਆਸਰਾ (ਲੋਕ ਪਰਲੋਕ ਵਿਚ ਸਹਾਇਤਾ ਕਰਦਾ ਹੈ)।",
      "translation_ru": "О моя душа! Опорой имени Всевышнего только и бывает поддержка в этом мире и в ином."
    },
    {
      "verse_id": 9032,
      "gurmukhi": "ਅਵਰੁ ਜਿ ਕਰਨ ਕਰਾਵਨੋ ਤਿਨ ਮਹਿ ਭਉ ਹੈ ਜਾਮ ਕਾ ॥੧॥ ਰਹਾਉ ॥",
      "roman": "Avar ji karan karāvano tin meh bhau hai jām kā.1. Rahāu.",
      "sahib_singh_pa": "(ਨਾਮ ਤੋਂ ਬਿਨਾ ਮਾਇਆ ਦੀ ਖ਼ਾਤਰ) ਹੋਰ ਜਿਤਨਾ ਭੀ ਉੱਦਮ-ਜਤਨ ਹੈ ਉਹਨਾਂ ਸਾਰੇ ਕੰਮਾਂ ਵਿਚ ਆਤਮਕ ਮੌਤ ਦਾ ਖ਼ਤਰਾ (ਬਣਦਾ ਜਾਂਦਾ ਹੈ) ॥੧॥ ਰਹਾਉ ॥",
      "translation_ru": "Кроме этого, сколько бы ни было иных усилий и стараний ради майи, во всех этих делах возрастает опасность духовной смерти. 1. Пауза."
    },
    {
      "verse_id": 9033,
      "gurmukhi": "ਅਵਰ ਜਤਨਿ ਨਹੀ ਪਾਈਐ ॥",
      "roman": "Avar jatan nahī pāīai",
      "sahib_singh_pa": "(ਸਿਮਰਨ ਤੋਂ ਬਿਨਾ ਕਿਸੇ ਭੀ) ਹੋਰ ਜਤਨ ਨਾਲ ਪਰਮਾਤਮਾ ਨਹੀਂ ਮਿਲਦਾ।",
      "translation_ru": "Никакими иными средствами Всевышнего не достичь."
    },
    {
      "verse_id": 9034,
      "gurmukhi": "ਵਡੈ ਭਾਗਿ ਹਰਿ ਧਿਆਈਐ ॥੧॥",
      "roman": "Vaḍai bhāg har dhiāīai.1.",
      "sahib_singh_pa": "(ਪਰ) ਵੱਡੀ ਕਿਸਮਤਿ ਨਾਲ ਹੀ ਪਰਮਾਤਮਾ ਦਾ ਸਿਮਰਨ ਕੀਤਾ ਜਾ ਸਕਦਾ ਹੈ ॥੧॥",
      "translation_ru": "Но лишь по великой удаче человек может предаваться памятованию о Хари. 1."
    },
    {
      "verse_id": 9035,
      "gurmukhi": "ਲਾਖ ਹਿਕਮਤੀ ਜਾਨੀਐ ॥",
      "roman": "Lākh hikmatī jānīai",
      "sahib_singh_pa": "(ਜੇ ਜਗਤ ਵਿਚ) ਲੱਖਾਂ ਚਤੁਰਾਈਆਂ ਦੇ ਕਾਰਨ ਇੱਜ਼ਤ ਖੱਟ ਲਈਏ,",
      "translation_ru": "Пусть даже в мире удастся приобрести почёт благодаря тысячам хитроумных уловок,"
    },
    {
      "verse_id": 9036,
      "gurmukhi": "ਆਗੈ ਤਿਲੁ ਨਹੀ ਮਾਨੀਐ ॥੨॥",
      "roman": "Āgai til nahī mānīai.2.",
      "sahib_singh_pa": "ਪਰਲੋਕ ਵਿਚ (ਇਹਨਾਂ ਹਿਕਮਤਾਂ ਦੇ ਕਾਰਨ) ਰਤਾ ਜਿਤਨਾ ਭੀ ਆਦਰ ਨਹੀਂ ਮਿਲਦਾ ॥੨॥",
      "translation_ru": "в ином мире из-за этих ухищрений не получишь и крупицы уважения. 2."
    },
    {
      "verse_id": 9037,
      "gurmukhi": "ਅਹੰਬੁਧਿ ਕਰਮ ਕਮਾਵਨੇ ॥ ਗ੍ਰਿਹ ਬਾਲੂ ਨੀਰਿ ਬਹਾਵਨੇ ॥੩॥",
      "roman": "Ahaṃbudh karam kamāvane. Grih bālū nīr bahāvane.3.",
      "sahib_singh_pa": "(ਹੇ ਜਿੰਦੇ! ਜੇ ਆਪਣੇ ਵਲੋਂ ਧਾਰਮਿਕ) ਕੰਮ (ਭੀ) ਕੀਤੇ ਜਾਣ (ਪਰ ਉਹ) ਹਉਮੈ ਵਾਲੀ ਅਕਲ ਵਧਾਣ ਵਾਲੇ ਹੀ ਹੋਣ, ਤਾਂ ਉਹ ਅਜੇਹੇ ਕਰਮ ਰੇਤ ਦੇ ਘਰਾਂ ਵਾਂਗ ਹੀ ਹਨ ਜਿਨ੍ਹਾਂ ਨੂੰ (ਹੜ੍ਹ ਦੇ) ਪਾਣੀ ਨੇ ਰੋੜ੍ਹ ਦਿੱਤਾ ॥੩॥",
      "translation_ru": "Если даже совершать религиозные дела, но они лишь питают разум, полный Хоумэ, тогда такие дела подобны домам из песка, которые смыло потоком воды. 3."
    },
    {
      "verse_id": 9038,
      "gurmukhi": "ਪ੍ਰਭੁ ਕ੍ਰਿਪਾਲੁ ਕਿਰਪਾ ਕਰੈ ॥",
      "roman": "Prabh kirpāl kirpā karai",
      "sahib_singh_pa": "ਦਇਆ ਦਾ ਸੋਮਾ ਪਰਮਾਤਮਾ ਜਿਸ ਮਨੁੱਖ ਉਤੇ ਕਿਰਪਾ ਕਰਦਾ ਹੈ,",
      "translation_ru": "Когда источник милости, Всевышний, оказывает человеку свою милость,"
    },
    {
      "verse_id": 9039,
      "gurmukhi": "ਨਾਮੁ ਨਾਨਕ ਸਾਧੂ ਸੰਗਿ ਮਿਲੈ ॥੪॥੪॥੧੪੨॥",
      "roman": "Nām Nānak sādhū sang milai.4.4.142.",
      "sahib_singh_pa": "ਹੇ ਨਾਨਕ! (ਆਖ-) ਉਸ ਨੂੰ ਗੁਰੂ ਦੀ ਸੰਗਤਿ ਵਿਚ ਪਰਮਾਤਮਾ ਦਾ ਨਾਮ ਮਿਲਦਾ ਹੈ ॥੪॥੪॥੧੪੨॥",
      "translation_ru": "тогда, о Нанак, в обществе Гуру он обретает имя Всевышнего. 4.4.142."
    },
    {
      "verse_id": 9040,
      "gurmukhi": "ਗਉੜੀ ਮਹਲਾ ੫ ॥",
      "roman": "Gauṛī mahalā 5",
      "sahib_singh_pa": "None",
      "translation_ru": ""
    },
    {
      "verse_id": 9041,
      "gurmukhi": "ਬਾਰਨੈ ਬਲਿਹਾਰਨੈ ਲਖ ਬਰੀਆ ॥",
      "roman": "Bārnai balihāranai lakh barīā",
      "sahib_singh_pa": "ਹੇ ਭਾਈ! ਮੈਂ (ਪਰਮਾਤਮਾ ਦੇ ਨਾਮ ਤੋਂ) ਲੱਖਾਂ ਵਾਰੀ ਸਦਕੇ ਜਾਂਦਾ ਹਾਂ, ਕੁਰਬਾਨ ਜਾਂਦਾ ਹਾਂ।",
      "translation_ru": "О брат! Я сотни тысяч раз иду в жертву, иду в посвящение."
    },
    {
      "verse_id": 9042,
      "gurmukhi": "ਨਾਮੋ ਹੋ ਨਾਮੁ ਸਾਹਿਬ ਕੋ ਪ੍ਰਾਨ ਅਧਰੀਆ ॥੧॥ ਰਹਾਉ ॥",
      "roman": "Nāmo ho nām sāhib ko prān adharīā.1. Rahāu.",
      "sahib_singh_pa": "ਮਾਲਕ-ਪ੍ਰਭੂ ਦਾ ਨਾਮ ਹੀ ਨਾਮ ਜੀਵਾਂ ਦੀਆਂ ਜਿੰਦਾਂ ਦਾ ਆਸਰਾ ਹੈ ॥੧॥ ਰਹਾਉ ॥",
      "translation_ru": "Одно лишь имя Господа-Владыки есть опора жизни всех существ. 1. Пауза."
    },
    {
      "verse_id": 9043,
      "gurmukhi": "ਕਰਨ ਕਰਾਵਨ ਤੁਹੀ ਏਕ ॥",
      "roman": "Karan karāvan tuhī ek",
      "sahib_singh_pa": "ਹੇ ਪ੍ਰਭੂ! ਸਿਰਫ਼ ਤੂੰ ਹੀ ਸਭ ਕੁਝ ਕਰਨ ਦੀ ਤਾਕਤ ਰੱਖਦਾ ਹੈਂ, ਜੀਵਾਂ ਪਾਸੋਂ ਕਰਾਣ ਦੀ ਸਮਰੱਥਾ ਰੱਖਦਾ ਹੈਂ।",
      "translation_ru": "О Господь! Только Ты один имеешь силу всё совершать и побуждать существ к действию."
    },
    {
      "verse_id": 9044,
      "gurmukhi": "ਜੀਅ ਜੰਤ ਕੀ ਤੁਹੀ ਟੇਕ ॥੧॥",
      "roman": "Jīa jant kī tuhī ṭek.1.",
      "sahib_singh_pa": "ਤੂੰ ਹੀ ਸਾਰੇ ਜੀਵਾਂ-ਜੰਤਾਂ ਦਾ ਸਹਾਰਾ ਹੈਂ ॥੧॥",
      "translation_ru": "Ты один поддержка всех живых существ. 1."
    },
    {
      "verse_id": 9045,
      "gurmukhi": "ਰਾਜ ਜੋਬਨ ਪ੍ਰਭ ਤੂੰ ਧਨੀ ॥ ਤੂੰ ਨਿਰਗੁਨ ਤੂੰ ਸਰਗੁਨੀ ॥੨॥",
      "roman": "Rāj joban prabh tūṃ dhanī. Tūṃ nirgun tūṃ sargunī.2.",
      "sahib_singh_pa": "ਹੇ ਪ੍ਰਭੂ! ਤੂੰ ਹੀ ਹਕੂਮਤ ਦਾ ਮਾਲਕ ਹੈਂ, ਤੂੰ ਹੀ ਜਵਾਨੀ ਦਾ ਮਾਲਕ ਹੈਂ (ਤੈਥੋਂ ਹੀ ਜੀਵ ਦੁਨੀਆ ਵਿਚ ਹਕੂਮਤ ਕਰਨ ਦੀ  ਦਾਤ ਲੈਂਦੇ ਹਨ, ਤੈਥੋਂ ਹੀ ਜਵਾਨੀ ਪ੍ਰਾਪਤ ਕਰਦੇ ਹਨ)। (ਜਦੋਂ ਜਗਤ ਨਹੀਂ ਸੀ ਬਣਿਆ) ਮਾਇਆ ਦੇ ਤਿੰਨਾਂ ਗੁਣਾਂ ਤੋਂ ਰਹਿਤ ਭੀ ਤੂੰ ਹੈਂ, (ਹੁਣ ਤੂੰ ਜਗਤ ਰਚ ਦਿੱਤਾ ਹੈ) ਇਹ ਦਿੱਸਦਾ ਆਕਾਰ ਮਾਇਆ ਦੇ ਤਿੰਨਾਂ ਗੁਣਾਂ ਵਾਲਾ-ਇਹ ਭੀ ਤੂੰ ਆਪ ਹੀ ਹੈਂ ॥੨॥",
      "translation_ru": "О Господь! Ты владыка власти, Ты владыка молодости. От Тебя существа получают дар властвовать в мире, от Тебя получают юность. Когда мира ещё не было, Ты был вне трёх качеств майи, и теперь, когда мир сотворён, этот видимый образ, исполненный трёх качеств майи, тоже есть Ты Сам. 2."
    },
    {
      "verse_id": 9046,
      "gurmukhi": "ਈਹਾ ਊਹਾ ਤੁਮ ਰਖੇ ॥",
      "roman": "Īhā ūhā tum rakhe",
      "sahib_singh_pa": "(ਹੇ ਪ੍ਰਭੂ! ਇਸ ਲੋਕ ਵਿਚ ਤੇ ਪਰਲੋਕ ਵਿਚ ਤੂੰ ਹੀ ਸਭ ਦੀ ਰੱਖਿਆ ਕਰਦਾ ਹੈਂ,",
      "translation_ru": "О Господь! И в этом мире, и в мире ином Ты один хранишь всех,"
    },
    {
      "verse_id": 9047,
      "gurmukhi": "ਗੁਰ ਕਿਰਪਾ ਤੇ ਕੋ ਲਖੇ ॥੩॥",
      "roman": "Gur kirpā te ko lakhē.3.",
      "sahib_singh_pa": "(ਪਰ) ਕੋਈ ਵਿਰਲਾ ਮਨੁੱਖ ਗੁਰੂ ਦੀ ਕਿਰਪਾ ਨਾਲ (ਇਹ ਭੇਤ) ਸਮਝਦਾ ਹੈ ॥੩॥",
      "translation_ru": "но лишь редкий человек по милости Гуру понимает эту тайну. 3."
    },
    {
      "verse_id": 9048,
      "gurmukhi": "ਅੰਤਰਜਾਮੀ ਪ੍ਰਭ ਸੁਜਾਨੁ ॥",
      "roman": "Antarjāmī prabh sujān",
      "sahib_singh_pa": "ਹੇ ਪ੍ਰਭੂ! ਤੂੰ ਸਭ ਦੇ ਦਿਲ ਦੀ ਜਾਣਨ ਵਾਲਾ ਹੈਂ, ਤੂੰ ਹੀ ਸਿਆਣਾ ਹੈਂ।",
      "translation_ru": "О Господь! Ты знаешь сердца всех, Ты один поистине мудр."
    },
    {
      "verse_id": 9049,
      "gurmukhi": "ਨਾਨਕ ਤਕੀਆ ਤੁਹੀ ਤਾਣੁ ॥੪॥੫॥੧੪੩॥",
      "roman": "Nānak takīā tuhī tāṇ.4.5.143.",
      "sahib_singh_pa": "ਨਾਨਕ ਦਾ ਸਹਾਰਾ ਤੂੰ ਹੀ ਹੈਂ, ਨਾਨਕ ਦਾ ਤਾਣ ਤੂੰ ਹੀ ਹੈਂ ॥੪॥੫॥੧੪੩॥",
      "translation_ru": "Ты один опора Нанаку, Ты один его сила. 4.5.143."
    },
    {
      "verse_id": 9050,
      "gurmukhi": "ਗਉੜੀ ਮਹਲਾ ੫ ॥",
      "roman": "Gauṛī mahalā 5",
      "sahib_singh_pa": "None",
      "translation_ru": ""
    },
    {
      "verse_id": 9051,
      "gurmukhi": "ਹਰਿ ਹਰਿ ਹਰਿ ਆਰਾਧੀਐ ॥",
      "roman": "Har har har ārādhīai",
      "sahib_singh_pa": "(ਹੇ ਭਾਈ!) ਸਦਾ ਪਰਮਾਤਮਾ ਦਾ ਨਾਮ ਸਿਮਰਨਾ ਚਾਹੀਦਾ ਹੈ।",
      "translation_ru": "О брат! Следует всегда созерцать имя Всевышнего."
    },
    {
      "verse_id": 9052,
      "gurmukhi": "ਸੰਤਸੰਗਿ ਹਰਿ ਮਨਿ ਵਸੈ ਭਰਮੁ ਮੋਹੁ ਭਉ ਸਾਧੀਐ ॥੧॥ ਰਹਾਉ ॥",
      "roman": "Santsang har man વસai bharam moh bhau sādhīai.1. Rahāu.",
      "sahib_singh_pa": "ਸੰਤਾਂ ਦੀ ਸੰਗਤਿ ਵਿਚ (ਹੀ) ਪਰਮਾਤਮਾ (ਮਨੁੱਖ ਦੇ) ਮਨ ਵਿਚ ਵੱਸ ਸਕਦਾ ਹੈ, ਭਟਕਣਾ ਨੂੰ, ਮੋਹ ਨੂੰ ਤੇ ਡਰ-ਸਹਮ ਨੂੰ ਕਾਬੂ ਕੀਤਾ ਜਾ ਸਕਦਾ ਹੈ ॥੧॥ ਰਹਾਉ ॥",
      "translation_ru": "Только в обществе святых Всевышний может поселиться в уме человека, и только так можно обуздать блуждание, привязанность и страх. 1. Пауза."
    },
    {
      "verse_id": 9053,
      "gurmukhi": "ਬੇਦ ਪੁਰਾਣ ਸਿਮ੍ਰਿਤਿ ਭਨੇ ॥",
      "roman": "Bed purāṇ simrit bhane",
      "sahib_singh_pa": "(ਹੇ ਭਾਈ! ਪੰਡਤ ਲੋਕ ਭਾਵੇਂ) ਵੇਦ ਪੁਰਾਣ ਸਿਮ੍ਰਿਤੀਆਂ (ਆਦਿਕ ਧਰਮ-ਪੁਸਤਕਾਂ) ਪੜ੍ਹਦੇ ਹਨ,",
      "translation_ru": "О брат! Пусть учёные и читают Веды, Пураны и Смрити,"
    },
    {
      "verse_id": 9054,
      "gurmukhi": "ਸਭ ਊਚ ਬਿਰਾਜਿਤ ਜਨ ਸੁਨੇ ॥੧॥",
      "roman": "Sabh ūch birājit jan sune.1.",
      "sahib_singh_pa": "ਪਰ ਸੰਤ ਜਨ ਹੋਰ ਸਭ ਲੋਕਾਂ ਤੋਂ ਉੱਚੇ ਆਤਮਕ ਟਿਕਾਣੇ ਤੇ ਟਿਕੇ ਹੋਏ ਸੁਣੇ ਜਾਂਦੇ ਹਨ ॥੧॥",
      "translation_ru": "но слышно, что святые пребывают на более высоком духовном уровне, чем все остальные. 1."
    },
    {
      "verse_id": 9055,
      "gurmukhi": "ਸਗਲ ਅਸਥਾਨ ਭੈ ਭੀਤ ਚੀਨ ॥",
      "roman": "Sagal asthān bhai bhīt chīn",
      "sahib_singh_pa": "(ਹੇ ਭਾਈ!) ਹੋਰ ਸਾਰੇ ਹਿਰਦੇ-ਥਾਂ ਡਰਾਂ ਨਾਲ ਸਹਮੇ ਹੋਏ ਵੇਖੀਦੇ ਹਨ,",
      "translation_ru": "О брат! Все прочие состояния сердца видятся исполненными страха и тревоги,"
    },
    {
      "verse_id": 9056,
      "gurmukhi": "ਰਾਮ ਸੇਵਕ ਭੈ ਰਹਤ ਕੀਨ ॥੨॥",
      "roman": "Rām sevak bhai rahat kīn.2.",
      "sahib_singh_pa": "(ਪਰਮਾਤਮਾ ਦੇ ਸਿਮਰਨ ਨੇ) ਪਰਮਾਤਮਾ ਦੇ ਭਗਤਾਂ ਨੂੰ ਡਰਾਂ ਤੋਂ ਰਹਿਤ ਕਰ ਦਿੱਤਾ ਹੈ ॥੨॥",
      "translation_ru": "а памятование о Всевышнем сделало Его слуг свободными от страха. 2."
    },
    {
      "verse_id": 9057,
      "gurmukhi": "ਲਖ ਚਉਰਾਸੀਹ ਜੋਨਿ ਫਿਰਹਿ ॥",
      "roman": "Lakh chaurāsīh jon fireh",
      "sahib_singh_pa": "(ਹੇ ਭਾਈ! ਜੀਵ) ਚੌਰਾਸੀ ਲੱਖ ਜੂਨਾਂ ਵਿਚ ਭਟਕਦੇ ਫਿਰਦੇ ਹਨ,",
      "translation_ru": "О брат! Живые существа блуждают по восьмидесяти четырём лакхам форм существования,"
    },
    {
      "verse_id": 9058,
      "gurmukhi": "ਗੋਬਿੰਦ ਲੋਕ ਨਹੀ ਜਨਮਿ ਮਰਹਿ ॥੩॥",
      "roman": "Gobind lok nahī janam mareh.3.",
      "sahib_singh_pa": "ਪਰ ਪਰਮਾਤਮਾ ਦੇ ਭਗਤ ਜਨਮ ਮਰਨ ਦੇ ਗੇੜ ਵਿਚ ਨਹੀਂ ਪੈਂਦੇ ॥੩॥",
      "translation_ru": "но преданные Всевышнего не попадают в круг рождения и смерти. 3."
    },
    {
      "verse_id": 9059,
      "gurmukhi": "ਬਲ ਬੁਧਿ ਸਿਆਨਪ ਹਉਮੈ ਰਹੀ ॥ ਹਰਿ ਸਾਧ ਸਰਣਿ ਨਾਨਕ ਗਹੀ ॥੪॥੬॥੧੪੪॥",
      "roman": "Bal budh siānap haumai rahī. Har sādh saraṇ Nānak gahī.4.6.144.",
      "sahib_singh_pa": "(ਜਿਨ੍ਹਾਂ ਮਨੁੱਖਾਂ ਨੇ) ਪਰਮਾਤਮਾ ਦਾ ਗੁਰੂ ਦਾ ਆਸਰਾ ਲੈ ਲਿਆ, ਉਹਨਾਂ ਦੇ ਅੰਦਰੋਂ ਹਉਮੈ ਦੂਰ ਹੋ ਜਾਂਦੀ ਹੈ। ਹੇ ਨਾਨਕ! ਉਹ ਆਪਣੀ ਤਾਕਤ ਦਾ ਆਪਣੀ ਅਕਲ ਦਾ ਆਪਣੀ ਸਿਆਣਪ ਦਾ ਆਸਰਾ ਨਹੀਂ ਲੈਂਦੇ ॥੪॥੬॥੧੪੪॥",
      "translation_ru": "У тех людей, что приняли опору Всевышнего через Гуру, Хоумэ исчезает изнутри. О Нанак! Они больше не опираются на свою силу, свой ум и свою сообразительность. 4.6.144."
    },
    {
      "verse_id": 9060,
      "gurmukhi": "ਗਉੜੀ ਮਹਲਾ ੫ ॥",
      "roman": "Gauṛī mahalā 5",
      "sahib_singh_pa": "None",
      "translation_ru": ""
    },
    {
      "verse_id": 9061,
      "gurmukhi": "ਮਨ ਰਾਮ ਨਾਮ ਗੁਨ ਗਾਈਐ ॥",
      "roman": "Man Rām nām gun gāīai",
      "sahib_singh_pa": "ਹੇ (ਮੇਰੇ) ਮਨ! (ਆ) ਪਰਮਾਤਮਾ ਦਾ ਨਾਮ ਸਿਮਰੀਏ, ਪਰਮਾਤਮਾ ਦੇ ਗੁਣ ਗਾਇਨ ਕਰੀਏ।",
      "translation_ru": "О мой ум! Давай вспоминать имя Всевышнего, давай воспевать качества Всевышнего."
    },
    {
      "verse_id": 9062,
      "gurmukhi": "ਨੀਤ ਨੀਤ ਹਰਿ ਸੇਵੀਐ ਸਾਸਿ ਸਾਸਿ ਹਰਿ ਧਿਆਈਐ ॥੧॥ ਰਹਾਉ ॥",
      "roman": "Nīt nīt har sevīai sās sās har dhiāīai.1. Rahāu.",
      "sahib_singh_pa": "(ਹੇ ਮਨ!) ਸਦਾ ਹੀ ਪਰਮਾਤਮਾ ਦੀ ਭਗਤੀ ਕਰਨੀ ਚਾਹੀਦੀ ਹੈ ॥੧॥ ਰਹਾਉ ॥",
      "translation_ru": "О ум! Следует всегда предаваться служению Всевышнему. 1. Пауза."
    },
    {
      "verse_id": 9063,
      "gurmukhi": "ਸੰਤਸੰਗਿ ਹਰਿ ਮਨਿ ਵਸੈ ॥",
      "roman": "Santsang har man વસai",
      "sahib_singh_pa": "(ਹੇ ਭਾਈ!) ਗੁਰੂ-ਸੰਤ ਦੀ ਸੰਗਤਿ ਵਿਚ (ਰਿਹਾਂ) ਪਰਮਾਤਮਾ (ਮਨੁੱਖ ਦੇ) ਮਨ ਵਿਚ ਆ ਵੱਸਦਾ ਹੈ।",
      "translation_ru": "О брат! В обществе Гуру-святого Всевышний поселяется в уме человека."
    },
    {
      "verse_id": 9064,
      "gurmukhi": "ਦੁਖੁ ਦਰਦੁ ਅਨੇਰਾ ਭ੍ਰਮੁ ਨਸੈ ॥੧॥",
      "roman": "Dukh dard anerā bharam nasai.1.",
      "sahib_singh_pa": "(ਜਿਸ ਦੇ ਮਨ ਵਿਚ ਵੱਸ ਪੈਂਦਾ ਹੈ ਉਸ ਦੇ ਅੰਦਰੋਂ) ਹਰੇਕ ਕਿਸਮ ਦਾ ਦੁੱਖ ਦਰਦ ਦੂਰ ਹੋ ਜਾਂਦਾ ਹੈ, ਮੋਹ ਦਾ ਹਨੇਰਾ ਦੂਰ ਹੋ ਜਾਂਦਾ ਹੈ, (ਮਾਇਆ ਦੀ ਖ਼ਾਤਰ) ਭਟਕਣਾ ਮੁੱਕ ਜਾਂਦੀ ਹੈ ॥੧॥",
      "translation_ru": "У того, в чьём уме Он поселяется, исчезают всякая боль и страдание, уходит тьма привязанности и прекращается блуждание ради майи. 1."
    },
    {
      "verse_id": 9065,
      "gurmukhi": "ਸੰਤ ਪ੍ਰਸਾਦਿ ਹਰਿ ਜਾਪੀਐ ॥ ਸੋ ਜਨੁ ਦੂਖਿ ਨ ਵਿਆਪੀਐ ॥੨॥",
      "roman": "Sant prasād har jāpīai. So jan dūkh na viāpīai.2.",
      "sahib_singh_pa": "(ਹੇ ਭਾਈ!) ਗੁਰੂ ਦੀ ਕਿਰਪਾ ਨਾਲ (ਹੀ) ਪਰਮਾਤਮਾ ਦਾ ਨਾਮ ਜਪਿਆ ਜਾ ਸਕਦਾ ਹੈ। (ਜੇਹੜਾ ਮਨੁੱਖ ਜਪਦਾ ਹੈ) ਉਹ ਮਨੁੱਖ ਕਿਸੇ ਕਿਸਮ ਦੇ ਦੁੱਖ ਵਿਚ ਨਹੀਂ ਘਿਰਦਾ ॥੨॥",
      "translation_ru": "О брат! Только по милости Гуру можно повторять имя Всевышнего. И тот, кто повторяет, не оказывается охвачен никаким страданием. 2."
    },
    {
      "verse_id": 9066,
      "gurmukhi": "ਜਾ ਕਉ ਗੁਰੁ ਹਰਿ ਮੰਤ੍ਰੁ ਦੇ ॥",
      "roman": "Jā kau gur har mantr de",
      "sahib_singh_pa": "(ਹੇ ਭਾਈ!) ਗੁਰੂ ਜਿਸ ਮਨੁੱਖ ਨੂੰ ਪਰਮਾਤਮਾ ਦਾ ਨਾਮ-ਮੰਤ੍ਰ ਦੇਂਦਾ ਹੈ,",
      "translation_ru": "О брат! Тому человеку, кому Гуру даёт мантру имени Всевышнего,"
    },
    {
      "verse_id": 9067,
      "gurmukhi": "ਸੋ ਉਬਰਿਆ ਮਾਇਆ ਅਗਨਿ ਤੇ ॥੩॥",
      "roman": "So ubariā māiā agan te.3.",
      "sahib_singh_pa": "ਉਹ ਮਨੁੱਖ ਮਾਇਆ ਦੀ (ਤ੍ਰਿਸ਼ਨਾ) ਅੱਗ (ਵਿਚ ਸੜਨ) ਤੋਂ ਬਚ ਜਾਂਦਾ ਹੈ ॥੩॥",
      "translation_ru": "удаётся спастись от сгорания в огне жажды майи. 3."
    },
    {
      "verse_id": 9068,
      "gurmukhi": "ਨਾਨਕ ਕਉ ਪ੍ਰਭ ਮਇਆ ਕਰਿ ॥",
      "roman": "Nānak kau prabh maiā kar",
      "sahib_singh_pa": "(ਹੇ ਪ੍ਰਭੂ! ਮੈਂ) ਨਾਨਕ ਉਤੇ ਕਿਰਪਾ ਕਰ,",
      "translation_ru": "О Господь! Окажи милость Нанаку,"
    },
    {
      "verse_id": 9069,
      "gurmukhi": "ਮੇਰੈ ਮਨਿ ਤਨਿ ਵਾਸੈ ਨਾਮੁ ਹਰਿ ॥੪॥੭॥੧੪੫॥",
      "roman": "Merai man tan vāsai nām har.4.7.145.",
      "sahib_singh_pa": "(ਤਾਂ ਕਿ) ਮੇਰੇ ਮਨ ਵਿਚ ਹਿਰਦੇ ਵਿਚ, ਹੇ ਹਰੀ! ਤੇਰਾ ਨਾਮ ਵੱਸ ਪਏ ॥੪॥੭॥੧੪੫॥",
      "translation_ru": "чтобы в моём уме и в моём сердце поселилось Твоё имя, о Хари. 4.7.145."
    },
    {
      "verse_id": 9070,
      "gurmukhi": "ਗਉੜੀ ਮਹਲਾ ੫ ॥",
      "roman": "Gauṛī mahalā 5",
      "sahib_singh_pa": "None",
      "translation_ru": ""
    },
    {
      "verse_id": 9071,
      "gurmukhi": "ਰਸਨਾ ਜਪੀਐ ਏਕੁ ਨਾਮ ॥",
      "roman": "Rasnā japīai ek nām",
      "sahib_singh_pa": "(ਹੇ ਭਾਈ!) ਜੀਭ ਨਾਲ ਹਰਿ-ਨਾਮ ਜਪਦੇ ਰਹਿਣਾ ਚਾਹੀਦਾ ਹੈ।",
      "translation_ru": "О брат! Следует непрестанно повторять языком одно имя Хари."
    },
    {
      "verse_id": 9072,
      "gurmukhi": "ਈਹਾ ਸੁਖੁ ਆਨੰਦੁ ਘਨਾ ਆਗੈ ਜੀਅ ਕੈ ਸੰਗਿ ਕਾਮ ॥੧॥ ਰਹਾਉ ॥",
      "roman": "Īhā sukh ānand ghanā āgai jīa kai sang kām.1. Rahāu.",
      "sahib_singh_pa": "(ਜੇ ਹਰਿ-ਨਾਮ ਜਪਦੇ ਰਹੀਏ ਤਾਂ) ਇਸ ਲੋਕ ਵਿਚ (ਇਸ ਜੀਵਨ ਵਿਚ) ਬਹੁਤ ਸੁਖ-ਆਨੰਦ ਮਿਲਦਾ ਹੈ ਤੇ ਪਰਲੋਕ ਵਿਚ (ਇਹ ਹਰਿ-ਨਾਮ) ਜਿੰਦ ਦੇ ਕੰਮ ਆਉਂਦਾ ਹੈ ॥੧॥ ਰਹਾਉ ॥",
      "translation_ru": "Если повторять имя Хари, то в этом мире приходит великое счастье и радость, а в мире ином это имя служит душе на пользу. 1. Пауза."
    },
    {
      "verse_id": 9073,
      "gurmukhi": "ਕਟੀਐ ਤੇਰਾ ਅਹੰ ਰੋਗੁ ॥",
      "roman": "Kaṭīai terā ahaṃ rog",
      "sahib_singh_pa": "(ਹੇ ਭਾਈ! ਹਰਿ-ਨਾਮ ਦੀ ਬਰਕਤਿ ਨਾਲ) ਤੇਰਾ ਹਉਮੈ ਦਾ ਰੋਗ ਕੱਟਿਆ ਜਾ ਸਕਦਾ ਹੈ।",
      "translation_ru": "О брат! Благодатью имени Хари может быть отсечена твоя болезнь Хоумэ."
    },
    {
      "verse_id": 9074,
      "gurmukhi": "ਤੂੰ ਗੁਰ ਪ੍ਰਸਾਦਿ ਕਰਿ ਰਾਜ ਜੋਗੁ ॥੧॥",
      "roman": "Tūṃ gur prasād kar rāj jog.1.",
      "sahib_singh_pa": "(ਨਾਮ ਜਪ ਜਪ ਕੇ) ਗੁਰੂ ਦੀ ਕਿਰਪਾ ਨਾਲ ਤੂੰ ਗ੍ਰਿਹਸਤ ਦਾ ਸੁਖ ਭੀ ਲੈ ਸਕਦਾ ਹੈਂ, ਤੇ ਪ੍ਰਭੂ ਨਾਲ ਮਿਲਾਪ ਭੀ ਪ੍ਰਾਪਤ ਕਰ ਸਕਦਾ ਹੈਂ ॥੧॥",
      "translation_ru": "Повторяя имя, по милости Гуру ты можешь и вкусить счастье домохозяйской жизни, и обрести соединение с Господом. 1."
    },
    {
      "verse_id": 9075,
      "gurmukhi": "ਹਰਿ ਰਸੁ ਜਿਨਿ ਜਨਿ ਚਾਖਿਆ ॥",
      "roman": "Har ras jin jan chākhiā",
      "sahib_singh_pa": "(ਹੇ ਭਾਈ!) ਜਿਸ ਮਨੁੱਖ ਨੇ ਪਰਮਾਤਮਾ ਦਾ ਨਾਮ-ਰਸ ਚੱਖ ਲਿਆ,",
      "translation_ru": "О брат! Тот человек, кто вкусил нектар имени Всевышнего,"
    },
    {
      "verse_id": 9076,
      "gurmukhi": "ਤਾ ਕੀ ਤ੍ਰਿਸਨਾ ਲਾਥੀਆ ॥੨॥",
      "roman": "Tā kī trisnā lāthīā.2.",
      "sahib_singh_pa": "ਉਸ ਦੀ (ਮਾਇਆ ਦੀ) ਤ੍ਰਿਸ਼ਨਾ ਲਹਿ ਜਾਂਦੀ ਹੈ ॥੨॥",
      "translation_ru": "освобождается от жажды майи. 2."
    },
    {
      "verse_id": 9077,
      "gurmukhi": "ਹਰਿ ਬਿਸ੍ਰਾਮ ਨਿਧਿ ਪਾਇਆ ॥",
      "roman": "Har bisrām nidh pāiā",
      "sahib_singh_pa": "(ਹੇ ਭਾਈ! ਜਿਸ ਮਨੁੱਖ ਨੇ ਹਰਿ-ਨਾਮ-ਰਸ ਚੱਖ ਲਿਆ) ਉਸ ਨੂੰ ਸ਼ਾਂਤੀ ਦਾ ਖ਼ਜ਼ਾਨਾ ਪਰਮਾਤਮਾ ਮਿਲ ਪਿਆ,",
      "translation_ru": "О брат! Тот, кто вкусил нектар имени Хари, находит Самого Всевышнего как сокровище покоя,"
    },
    {
      "verse_id": 9078,
      "gurmukhi": "ਸੋ ਬਹੁਰਿ ਨ ਕਤ ਹੀ ਧਾਇਆ ॥੩॥",
      "roman": "So bahur na kat hī dhāiā.3.",
      "sahib_singh_pa": "ਉਹ ਮਨੁੱਖ ਮੁੜ ਕਿਸੇ ਭੀ ਹੋਰ ਪਾਸੇ ਭਟਕਦਾ ਨਹੀਂ ਫਿਰਦਾ ॥੩॥",
      "translation_ru": "и такой человек уже больше никуда не мечется и не блуждает. 3."
    },
    {
      "verse_id": 9079,
      "gurmukhi": "ਹਰਿ ਹਰਿ ਨਾਮੁ ਜਾ ਕਉ ਗੁਰਿ ਦੀਆ ॥",
      "roman": "Har har nām jā kau gur dīā",
      "sahib_singh_pa": "ਜਿਸ ਮਨੁੱਖ ਨੂੰ ਗੁਰੂ ਨੇ ਪਰਮਾਤਮਾ ਦਾ ਨਾਮ ਬਖ਼ਸ਼ ਦਿੱਤਾ,",
      "translation_ru": "Тому человеку, которому Гуру даровал имя Всевышнего,"
    },
    {
      "verse_id": 9080,
      "gurmukhi": "ਨਾਨਕ ਤਾ ਕਾ ਭਉ ਗਇਆ ॥੪॥੮॥੧੪੬॥",
      "roman": "Nānak tā kā bhau gaiā.4.8.146.",
      "sahib_singh_pa": "(ਹੇ ਨਾਨਕ) ਉਸ ਦਾ ਹਰੇਕ ਕਿਸਮ ਦਾ ਡਰ ਦੂਰ ਹੋ ਗਿਆ ॥੪॥੮॥੧੪੬॥",
      "translation_ru": "о Нанак, исчез всякий страх. 4.8.146."
    }
  ]
}