{
  "ang": 410,
  "line_count": 75,
  "lines": [
    {
      "index": 0,
      "verse_id": 18686,
      "shabad_num": 0,
      "shabad_id": null,
      "gurmukhi": "ਅਲਖ ਅਭੇਵੀਐ ਹਾਂ ॥",
      "site_roman": "",
      "sahib_singh_pa": "ਜਿਸ ਦਾ ਸਹੀ-ਸਰੂਪ ਦੱਸਿਆ ਨਹੀਂ ਜਾ ਸਕਦਾ ਤੇ ਜਿਸ ਦਾ ਭੇਤ ਪਾਇਆ ਨਹੀਂ ਜਾ ਸਕਦਾ।",
      "roman": "alakh abhevīai hāṅ",
      "translation_ru": "Чей истинный облик нельзя описать и Чью тайну нельзя постичь."
    },
    {
      "index": 0,
      "verse_id": 18687,
      "shabad_num": 0,
      "shabad_id": null,
      "gurmukhi": "ਤਾਂ ਸਿਉ ਪ੍ਰੀਤਿ ਕਰਿ ਹਾਂ ॥",
      "site_roman": "",
      "sahib_singh_pa": "(ਹੇ ਮੇਰੇ ਮਨ!) ਉਸ ਪਰਮਾਤਮਾ ਨਾਲ ਪਿਆਰ ਪਾ,",
      "roman": "tāṅ siu prīt kar hāṅ",
      "translation_ru": "О мой ум! Возлюби этого Параматму,"
    },
    {
      "index": 0,
      "verse_id": 18688,
      "shabad_num": 0,
      "shabad_id": null,
      "gurmukhi": "ਬਿਨਸਿ ਨ ਜਾਇ ਮਰਿ ਹਾਂ ॥",
      "site_roman": "",
      "sahib_singh_pa": "ਜੇਹੜਾ ਕਦੇ ਨਾਸ ਨਹੀਂ ਹੁੰਦਾ ਜੋ ਨਾਹ ਜੰਮਦਾ ਹੈ ਤੇ ਨਾਹ ਮਰਦਾ ਹੈ।",
      "roman": "binas na jāi mar hāṅ",
      "translation_ru": "Который никогда не уничтожается, не рождается и не умирает."
    },
    {
      "index": 0,
      "verse_id": 18689,
      "shabad_num": 0,
      "shabad_id": null,
      "gurmukhi": "ਗੁਰ ਤੇ ਜਾਨਿਆ ਹਾਂ ॥",
      "site_roman": "",
      "sahib_singh_pa": "ਜਿਸ ਮਨੁੱਖ ਨੇ ਗੁਰੂ ਦੀ ਰਾਹੀਂ ਉਸ ਪਰਮਾਤਮਾ ਨਾਲ ਡੂੰਘੀ ਸਾਂਝ ਪਾ ਲਈ,",
      "roman": "gur te jāniā hāṅ",
      "translation_ru": "Тот человек, который через Гуру обрёл глубокую связь с этим Параматмой,"
    },
    {
      "index": 0,
      "verse_id": 18690,
      "shabad_num": 0,
      "shabad_id": null,
      "gurmukhi": "ਨਾਨਕ ਮਨੁ ਮਾਨਿਆ ਮੇਰੇ ਮਨਾ ॥੨॥੩॥੧੫੯॥",
      "site_roman": "",
      "sahib_singh_pa": "ਹੇ ਨਾਨਕ! (ਆਖ-) ਹੇ ਮੇਰੇ ਮਨ! ਉਸ ਦਾ ਮਨ ਸਦਾ (ਉਸ ਦੀ ਯਾਦ ਵਿਚ) ਗਿੱਝ ਜਾਂਦਾ ਹੈ ॥੨॥੩॥੧੫੯॥",
      "roman": "nānak man māniā mere manā.2.3.159.",
      "translation_ru": "О Нанак, скажи: о мой ум, его ум навсегда проникается этой памятью. ॥2॥3॥159॥"
    },
    {
      "index": 0,
      "verse_id": 18691,
      "shabad_num": 0,
      "shabad_id": null,
      "gurmukhi": "ਆਸਾਵਰੀ ਮਹਲਾ ੫ ॥",
      "site_roman": "",
      "sahib_singh_pa": "None",
      "roman": "āsāvarī mehlā 5",
      "translation_ru": ""
    },
    {
      "index": 0,
      "verse_id": 18692,
      "shabad_num": 0,
      "shabad_id": null,
      "gurmukhi": "ਏਕਾ ਓਟ ਗਹੁ ਹਾਂ ॥",
      "site_roman": "",
      "sahib_singh_pa": "ਹੇ ਮੇਰੇ ਮਨ! ਇਕ ਪਰਮਾਤਮਾ ਦਾ ਪੱਲਾ ਫੜ,",
      "roman": "ekā oṭ gah̃ hā̃",
      "translation_ru": "О мой ум! Держись только за одного Параматму."
    },
    {
      "index": 0,
      "verse_id": 18693,
      "shabad_num": 0,
      "shabad_id": null,
      "gurmukhi": "ਗੁਰ ਕਾ ਸਬਦੁ ਕਹੁ ਹਾਂ ॥",
      "site_roman": "",
      "sahib_singh_pa": "ਸਦਾ ਗੁਰੂ ਦੀ ਬਾਣੀ ਉਚਾਰਦਾ ਰਹੁ।",
      "roman": "gur kā sabad kah̃ hā̃",
      "translation_ru": "Постоянно произноси Бани Гуру."
    },
    {
      "index": 0,
      "verse_id": 18694,
      "shabad_num": 0,
      "shabad_id": null,
      "gurmukhi": "ਆਗਿਆ ਸਤਿ ਸਹੁ ਹਾਂ ॥",
      "site_roman": "",
      "sahib_singh_pa": "ਪਰਮਾਤਮਾ ਦੀ ਰਜ਼ਾ ਨੂੰ ਮਿੱਠੀ ਕਰ ਕੇ ਮੰਨ।",
      "roman": "āgiā sat sah̃ hā̃",
      "translation_ru": "Сладостно прими и признай волю Параматмы."
    },
    {
      "index": 0,
      "verse_id": 18695,
      "shabad_num": 0,
      "shabad_id": null,
      "gurmukhi": "ਮਨਹਿ ਨਿਧਾਨੁ ਲਹੁ ਹਾਂ ॥",
      "site_roman": "",
      "sahib_singh_pa": "ਆਪਣੇ ਮਨ ਵਿਚ ਵੱਸਦੇ ਸਾਰੇ ਗੁਣਾਂ ਦੇ ਖ਼ਜ਼ਾਨੇ ਪ੍ਰਭੂ ਨੂੰ ਲੱਭ ਲੈ।",
      "roman": "manah nidhān lah̃ hā̃",
      "translation_ru": "Найди в своём уме Господа, в Котором пребывает сокровищница всех добродетелей."
    },
    {
      "index": 0,
      "verse_id": 18696,
      "shabad_num": 0,
      "shabad_id": null,
      "gurmukhi": "ਸੁਖਹਿ ਸਮਾਈਐ ਮੇਰੇ ਮਨਾ ॥੧॥ ਰਹਾਉ ॥",
      "site_roman": "",
      "sahib_singh_pa": "ਹੇ ਮੇਰੇ ਮਨ! (ਇਸ ਤਰ੍ਹਾਂ ਸਦਾ) ਆਤਮਕ ਆਨੰਦ ਵਿਚ ਲੀਨ ਰਹੀਦਾ ਹੈ ॥੧॥ ਰਹਾਉ ॥",
      "roman": "sukhhī samāīai mere manā ǁ1ǁ rahāu",
      "translation_ru": "О мой ум! Так всегда и пребывают погружёнными в духовное блаженство. ॥1॥ Рахау ॥"
    },
    {
      "index": 0,
      "verse_id": 18697,
      "shabad_num": 0,
      "shabad_id": null,
      "gurmukhi": "ਜੀਵਤ ਜੋ ਮਰੈ ਹਾਂ ॥",
      "site_roman": "",
      "sahib_singh_pa": "ਜੇਹੜਾ ਮਨੁੱਖ ਕਿਰਤ-ਕਾਰ ਕਰਦਾ ਹੋਇਆ ਮਾਇਆ ਦੇ ਮੋਹ ਵਲੋਂ ਅਛੋਹ ਰਹਿੰਦਾ ਹੈ,",
      "roman": "jīvat jo marē hā̃",
      "translation_ru": "Тот человек, который, занимаясь делами, остаётся незатронутым привязанностью к майе,"
    },
    {
      "index": 0,
      "verse_id": 18698,
      "shabad_num": 0,
      "shabad_id": null,
      "gurmukhi": "ਦੁਤਰੁ ਸੋ ਤਰੈ ਹਾਂ ॥",
      "site_roman": "",
      "sahib_singh_pa": "ਉਹ ਮਨੁੱਖ ਇਸ ਸੰਸਾਰ-ਸਮੁੰਦਰ ਤੋਂ ਪਾਰ ਲੰਘ ਜਾਂਦਾ ਹੈ, ਜਿਸ ਵਿਚੋਂ ਪਾਰ ਲੰਘਣਾ ਬਹੁਤ ਔਖਾ ਹੈ,",
      "roman": "dutar so tarē hā̃",
      "translation_ru": "переплывает этот мирской океан, который очень трудно переплыть,"
    },
    {
      "index": 0,
      "verse_id": 18699,
      "shabad_num": 0,
      "shabad_id": null,
      "gurmukhi": "ਸਭ ਕੀ ਰੇਨੁ ਹੋਇ ਹਾਂ ॥",
      "site_roman": "",
      "sahib_singh_pa": "ਜੇ ਉਹ ਮਨੁੱਖ ਸਭਨਾਂ ਦੇ ਚਰਨਾਂ ਦੀ ਧੂੜ ਹੋਇਆ ਰਹਿੰਦਾ ਹੈ।",
      "roman": "sabh kī ren hoi hā̃",
      "translation_ru": "если он остаётся пылью у стоп всех."
    },
    {
      "index": 0,
      "verse_id": 18700,
      "shabad_num": 0,
      "shabad_id": null,
      "gurmukhi": "ਨਿਰਭਉ ਕਹਉ ਸੋਇ ਹਾਂ ॥",
      "site_roman": "",
      "sahib_singh_pa": "ਜੇ ਮੈਂ ਭੀ ਉਸ ਨਿਰਭਉ ਪਰਮਾਤਮਾ ਦੀ ਸਿਫ਼ਤ-ਸਾਲਾਹ ਕਰਦਾ ਰਹਾਂ,",
      "roman": "nirbhau kahau soi hā̃",
      "translation_ru": "Если и я буду постоянно воспевать того Нирбхау Параматму,"
    },
    {
      "index": 0,
      "verse_id": 18701,
      "shabad_num": 0,
      "shabad_id": null,
      "gurmukhi": "ਮਿਟੇ ਅੰਦੇਸਿਆ ਹਾਂ ॥",
      "site_roman": "",
      "sahib_singh_pa": "ਤਾਂ ਮੇਰੇ ਸਾਰੇ ਚਿੰਤਾ ਫ਼ਿਕਰ ਮਿਟ ਜਾਣਗੇ।",
      "roman": "miṭe andesiā hā̃",
      "translation_ru": "тогда исчезнут все мои тревоги и заботы."
    },
    {
      "index": 0,
      "verse_id": 18702,
      "shabad_num": 0,
      "shabad_id": null,
      "gurmukhi": "ਸੰਤ ਉਪਦੇਸਿਆ ਮੇਰੇ ਮਨਾ ॥੧॥",
      "site_roman": "",
      "sahib_singh_pa": "ਹੇ ਮੇਰੇ ਮਨ! (ਆਖ!) ਤੈਨੂੰ ਸਤਿਗੁਰੂ ਦੀ ਇਹ ਸਿੱਖਿਆ ਪ੍ਰਾਪਤ ਹੋ ਜਾਵੇ ॥੧॥",
      "roman": "sant updesiā mere manā ǁ1ǁ",
      "translation_ru": "О мой ум! Скажи: пусть тебе будет даровано это наставление Сатгуру. ॥1॥"
    },
    {
      "index": 0,
      "verse_id": 18703,
      "shabad_num": 0,
      "shabad_id": null,
      "gurmukhi": "ਜਿਸੁ ਜਨ ਨਾਮ ਸੁਖੁ ਹਾਂ ॥",
      "site_roman": "",
      "sahib_singh_pa": "ਜਿਸ ਮਨੁੱਖ ਨੂੰ ਪਰਮਾਤਮਾ ਦੇ ਨਾਮ ਦਾ ਆਨੰਦ ਪ੍ਰਾਪਤ ਹੋ ਜਾਂਦਾ ਹੈ,",
      "roman": "jis jan nām sukh hā̃",
      "translation_ru": "Человек, получивший радость Имени Параматмы,"
    },
    {
      "index": 0,
      "verse_id": 18704,
      "shabad_num": 0,
      "shabad_id": null,
      "gurmukhi": "ਤਿਸੁ ਨਿਕਟਿ ਨ ਕਦੇ ਦੁਖੁ ਹਾਂ ॥",
      "site_roman": "",
      "sahib_singh_pa": "ਕਦੇ ਕੋਈ ਦੁੱਖ ਉਸ ਦੇ ਨੇੜੇ ਨਹੀਂ ਢੁੱਕਦਾ।",
      "roman": "tis nikaṭ na kade dukh hā̃",
      "translation_ru": "никогда не подпускает к себе никакое страдание."
    },
    {
      "index": 0,
      "verse_id": 18705,
      "shabad_num": 0,
      "shabad_id": null,
      "gurmukhi": "ਜੋ ਹਰਿ ਹਰਿ ਜਸੁ ਸੁਨੇ ਹਾਂ ॥",
      "site_roman": "",
      "sahib_singh_pa": "ਜੇਹੜਾ ਮਨੁੱਖ ਪਰਮਾਤਮਾ ਦੀ ਸਿਫ਼ਤ-ਸਾਲਾਹ ਸਦਾ ਸੁਣਦਾ ਰਹਿੰਦਾ ਹੈ,",
      "roman": "jo har har jas sune hā̃",
      "translation_ru": "Тот человек, который постоянно слушает хвалу Параматмы,"
    },
    {
      "index": 0,
      "verse_id": 18706,
      "shabad_num": 0,
      "shabad_id": null,
      "gurmukhi": "ਸਭੁ ਕੋ ਤਿਸੁ ਮੰਨੇ ਹਾਂ ॥",
      "site_roman": "",
      "sahib_singh_pa": "(ਦੁਨੀਆ ਵਿਚ) ਹਰੇਕ ਮਨੁੱਖ ਉਸ ਦਾ ਆਦਰ-ਸਤਕਾਰ ਕਰਦਾ ਹੈ।",
      "roman": "sabh ko tis manne hā̃",
      "translation_ru": "почитается каждым человеком в мире."
    },
    {
      "index": 0,
      "verse_id": 18707,
      "shabad_num": 0,
      "shabad_id": null,
      "gurmukhi": "ਸਫਲੁ ਸੁ ਆਇਆ ਹਾਂ ॥",
      "site_roman": "",
      "sahib_singh_pa": "ਜਗਤ ਵਿਚ ਜੰਮਿਆ ਹੋਇਆ ਉਹੀ ਮਨੁੱਖ ਕਾਮਯਾਬ ਜੀਵਨ ਵਾਲਾ ਹੈ,",
      "roman": "safal su āiā hā̃",
      "translation_ru": "По-настоящему успешную жизнь прожил только тот,"
    },
    {
      "index": 0,
      "verse_id": 18708,
      "shabad_num": 0,
      "shabad_id": null,
      "gurmukhi": "ਨਾਨਕ ਪ੍ਰਭ ਭਾਇਆ ਮੇਰੇ ਮਨਾ ॥੨॥੪॥੧੬੦॥",
      "site_roman": "",
      "sahib_singh_pa": "ਹੇ ਨਾਨਕ! (ਆਖ-) ਹੇ ਮੇਰੇ ਮਨ! ਜੇਹੜਾ ਪਰਮਾਤਮਾ ਨੂੰ ਪਿਆਰਾ ਲੱਗ ਗਿਆ ਹੈ ॥੨॥੪॥੧੬੦॥",
      "roman": "nānak prabh bhāiā mere manā ǁ2ǁ4ǁ160ǁ",
      "translation_ru": "О Нанак! Скажи: о мой ум! тот, кто стал дорог Параматме. ॥2॥4॥160॥"
    },
    {
      "index": 0,
      "verse_id": 18709,
      "shabad_num": 0,
      "shabad_id": null,
      "gurmukhi": "ਆਸਾਵਰੀ ਮਹਲਾ ੫ ॥",
      "site_roman": "",
      "sahib_singh_pa": "None",
      "roman": "āsāvarī mehlā 5",
      "translation_ru": ""
    },
    {
      "index": 0,
      "verse_id": 18710,
      "shabad_num": 0,
      "shabad_id": null,
      "gurmukhi": "ਮਿਲਿ ਹਰਿ ਜਸੁ ਗਾਈਐ ਹਾਂ ॥",
      "site_roman": "",
      "sahib_singh_pa": "(ਸਾਧ ਸੰਗਤਿ ਵਿਚ) ਮਿਲ ਕੇ ਪਰਮਾਤਮਾ ਦੀ ਸਿਫ਼ਤ-ਸਾਲਾਹ ਦਾ ਗੀਤ ਗਾਣਾ ਚਾਹੀਦਾ ਹੈ,",
      "roman": "mil har jas gāīai hā̃",
      "translation_ru": "Собравшись вместе в Садх Сангат, следует петь песнь хвалы Параматмы,"
    },
    {
      "index": 0,
      "verse_id": 18711,
      "shabad_num": 0,
      "shabad_id": null,
      "gurmukhi": "ਪਰਮ ਪਦੁ ਪਾਈਐ ਹਾਂ ॥",
      "site_roman": "",
      "sahib_singh_pa": "(ਇਸ ਤਰ੍ਹਾਂ) ਆਤਮਕ ਜੀਵਨ ਦਾ ਸਭ ਤੋਂ ਉੱਚਾ ਦਰਜਾ ਹਾਸਲ ਕਰ ਲਈਦਾ ਹੈ।",
      "roman": "param pad pāīai hā̃",
      "translation_ru": "так достигается высшее состояние духовной жизни."
    },
    {
      "index": 0,
      "verse_id": 18712,
      "shabad_num": 0,
      "shabad_id": null,
      "gurmukhi": "ਉਆ ਰਸ ਜੋ ਬਿਧੇ ਹਾਂ ॥",
      "site_roman": "",
      "sahib_singh_pa": "ਜਿਹੜਾ ਮਨੁੱਖ (ਸਿਫ਼ਤ-ਸਾਲਾਹ ਦੇ) ਉਸ ਸੁਆਦ ਵਿਚ ਵਿੱਝ ਜਾਂਦਾ ਹੈ,",
      "roman": "uā ras jo bidhe hā̃",
      "translation_ru": "Тот человек, который пронзён тем вкусом хвалы,"
    },
    {
      "index": 0,
      "verse_id": 18713,
      "shabad_num": 0,
      "shabad_id": null,
      "gurmukhi": "ਤਾ ਕਉ ਸਗਲ ਸਿਧੇ ਹਾਂ ॥",
      "site_roman": "",
      "sahib_singh_pa": "ਉਸ ਨੂੰ (ਮਾਨੋ) ਸਾਰੀਆਂ ਸਿੱਧੀਆਂ ਪ੍ਰਾਪਤ ਹੋ ਜਾਂਦੀਆਂ ਹਨ।",
      "roman": "tā kau sagal sidhe hā̃",
      "translation_ru": "словно получает все сиддхи."
    },
    {
      "index": 0,
      "verse_id": 18714,
      "shabad_num": 0,
      "shabad_id": null,
      "gurmukhi": "ਅਨਦਿਨੁ ਜਾਗਿਆ ਹਾਂ ॥",
      "site_roman": "",
      "sahib_singh_pa": "ਜੋ ਹਰ ਵੇਲੇ (ਵਿਕਾਰਾਂ ਦੇ ਹੱਲਿਆਂ ਵਲੋਂ) ਸੁਚੇਤ ਰਹਿੰਦਾ ਹੈ (ਜਿਹੜਾ ਪ੍ਰਭੂ ਦੀ ਸਿਫ਼ਤ-ਸਾਲਾਹ ਕਰਦਾ ਹੈ),",
      "roman": "andin jāgiā hā̃",
      "translation_ru": "Кто всегда остаётся бодрствующим по отношению к натиску пороков, то есть воспевает Господа,"
    },
    {
      "index": 0,
      "verse_id": 18715,
      "shabad_num": 0,
      "shabad_id": null,
      "gurmukhi": "ਨਾਨਕ ਬਡਭਾਗਿਆ ਮੇਰੇ ਮਨਾ ॥੧॥ ਰਹਾਉ ॥",
      "site_roman": "",
      "sahib_singh_pa": "ਹੇ ਨਾਨਕ! (ਆਖ-) ਹੇ ਮੇਰੇ ਮਨ! ਉਹ ਮਨੁੱਖ ਵੱਡੇ ਭਾਗਾਂ ਵਾਲਾ ਹੋ ਜਾਂਦਾ ਹੈ ॥੧॥ ਰਹਾਉ ॥",
      "roman": "nānak baḍbhāgiā mere manā ǁ1ǁ rahāu",
      "translation_ru": "О Нанак! Скажи: о мой ум! такой человек становится очень удачливым. ॥1॥ Рахау ॥"
    },
    {
      "index": 0,
      "verse_id": 18716,
      "shabad_num": 0,
      "shabad_id": null,
      "gurmukhi": "ਸੰਤ ਪਗ ਧੋਈਐ ਹਾਂ ॥",
      "site_roman": "",
      "sahib_singh_pa": "ਸੰਤ ਜਨਾਂ ਦੇ ਚਰਨ ਧੋਣੇ ਚਾਹੀਦੇ ਹਨ (ਆਪਾ-ਭਾਵ ਛੱਡ ਕੇ ਸੰਤਾਂ ਦੀ ਸਰਨ ਪੈਣਾ ਚਾਹੀਦਾ ਹੈ),",
      "roman": "sant pag dhoīai hā̃",
      "translation_ru": "Следует омывать стопы святых, то есть, отбросив чувство своего я, искать прибежища у святых,"
    },
    {
      "index": 0,
      "verse_id": 18717,
      "shabad_num": 0,
      "shabad_id": null,
      "gurmukhi": "ਦੁਰਮਤਿ ਖੋਈਐ ਹਾਂ ॥",
      "site_roman": "",
      "sahib_singh_pa": "(ਇਸ ਤਰ੍ਹਾਂ ਮਨ ਦੀ) ਖੋਟੀ ਮਤਿ ਦੂਰ ਹੋ ਜਾਂਦੀ ਹੈ।",
      "roman": "durmat khoīai hā̃",
      "translation_ru": "так дурной ум исчезает."
    },
    {
      "index": 0,
      "verse_id": 18718,
      "shabad_num": 0,
      "shabad_id": null,
      "gurmukhi": "ਦਾਸਹ ਰੇਨੁ ਹੋਇ ਹਾਂ ॥",
      "site_roman": "",
      "sahib_singh_pa": "ਪ੍ਰਭੂ ਦੇ ਸੇਵਕਾਂ ਦੀ ਚਰਨ-ਧੂੜ ਬਣਿਆ ਰਹੁ,",
      "roman": "dāsah ren hoi hā̃",
      "translation_ru": "Оставайся пылью у стоп слуг Господа,"
    },
    {
      "index": 0,
      "verse_id": 18719,
      "shabad_num": 0,
      "shabad_id": null,
      "gurmukhi": "ਬਿਆਪੈ ਦੁਖੁ ਨ ਕੋਇ ਹਾਂ ॥",
      "site_roman": "",
      "sahib_singh_pa": "(ਇਸ ਤਰ੍ਹਾਂ) ਕੋਈ ਦੁੱਖ ਆਪਣਾ ਜ਼ੋਰ ਨਹੀਂ ਪਾ ਸਕਦਾ।",
      "roman": "biāpē dukh na koi hā̃",
      "translation_ru": "и тогда никакое страдание не сможет навязать свою силу."
    },
    {
      "index": 0,
      "verse_id": 18720,
      "shabad_num": 0,
      "shabad_id": null,
      "gurmukhi": "ਭਗਤਾਂ ਸਰਨਿ ਪਰੁ ਹਾਂ ॥",
      "site_roman": "",
      "sahib_singh_pa": "ਭਗਤ-ਜਨਾਂ ਦੀ ਸਰਨੀਂ ਪਿਆ ਰਹੁ,",
      "roman": "bhagtā̃ saran par hā̃",
      "translation_ru": "Оставайся в прибежище бхагатов,"
    },
    {
      "index": 0,
      "verse_id": 18721,
      "shabad_num": 0,
      "shabad_id": null,
      "gurmukhi": "ਜਨਮਿ ਨ ਕਦੇ ਮਰੁ ਹਾਂ ॥",
      "site_roman": "",
      "sahib_singh_pa": "ਜਨਮ ਮਰਨ ਦਾ ਗੇੜ ਨਹੀਂ ਰਹੇਗਾ।",
      "roman": "janam na kade mar hā̃",
      "translation_ru": "и круг рождения и смерти прекратится."
    },
    {
      "index": 0,
      "verse_id": 18722,
      "shabad_num": 0,
      "shabad_id": null,
      "gurmukhi": "ਅਸਥਿਰੁ ਸੇ ਭਏ ਹਾਂ ॥",
      "site_roman": "",
      "sahib_singh_pa": "ਉਹ ਅਡੋਲ ਆਤਮਕ ਜੀਵਨ ਵਾਲੇ ਬਣ ਜਾਂਦੇ ਹਨ,",
      "roman": "asthir se bhae hā̃",
      "translation_ru": "Они становятся обладателями устойчивой духовной жизни,"
    },
    {
      "index": 0,
      "verse_id": 18723,
      "shabad_num": 0,
      "shabad_id": null,
      "gurmukhi": "ਹਰਿ ਹਰਿ ਜਿਨੑ ਜਪਿ ਲਏ ਮੇਰੇ ਮਨਾ ॥੧॥",
      "site_roman": "",
      "sahib_singh_pa": "ਹੇ ਮੇਰੇ ਮਨ! ਜੇਹੜੇ ਮਨੁੱਖ ਸਦਾ ਪਰਮਾਤਮਾ ਦਾ ਨਾਮ ਜਪਦੇ ਹਨ ॥੧॥",
      "roman": "har har jinh japi lae mere manā ǁ1ǁ",
      "translation_ru": "О мой ум! те люди, которые постоянно повторяют Имя Параматмы. ॥1॥"
    },
    {
      "index": 0,
      "verse_id": 18724,
      "shabad_num": 0,
      "shabad_id": null,
      "gurmukhi": "ਸਾਜਨੁ ਮੀਤੁ ਤੂੰ ਹਾਂ ॥",
      "site_roman": "",
      "sahib_singh_pa": "(ਹੇ ਮੇਰੇ ਪ੍ਰਭੂ!) ਤੂੰ ਹੀ (ਮੇਰਾ) ਸੱਜਣ ਹੈਂ, ਤੂੰ ਹੀ (ਮੇਰਾ) ਮਿੱਤਰ ਹੈਂ,",
      "roman": "sājan mīt tū̃ hā̃",
      "translation_ru": "О мой Господь! Ты один мой близкий, Ты один мой друг,"
    },
    {
      "index": 0,
      "verse_id": 18725,
      "shabad_num": 0,
      "shabad_id": null,
      "gurmukhi": "ਨਾਮੁ ਦ੍ਰਿੜਾਇ ਮੂੰ ਹਾਂ ॥",
      "site_roman": "",
      "sahib_singh_pa": "ਮੈਨੂੰ (ਮੇਰੇ ਹਿਰਦੇ ਵਿਚ ਆਪਣਾ) ਨਾਮ ਪੱਕਾ ਕਰ ਕੇ ਟਿਕਾ ਦੇਹ।",
      "roman": "nām driṛāi mū̃ hā̃",
      "translation_ru": "утверди во мне, в моём сердце, Своё Имя."
    },
    {
      "index": 0,
      "verse_id": 18726,
      "shabad_num": 0,
      "shabad_id": null,
      "gurmukhi": "ਤਿਸੁ ਬਿਨੁ ਨਾਹਿ ਕੋਇ ਹਾਂ ॥",
      "site_roman": "",
      "sahib_singh_pa": "ਜਿਸ ਪਰਮਾਤਮਾ ਤੋਂ ਬਿਨਾ ਹੋਰ ਕੋਈ (ਅਸਲ ਸੱਜਣ ਮਿੱਤਰ) ਨਹੀਂ ਹੈ,",
      "roman": "tis bin nāh koi hā̃",
      "translation_ru": "Кроме того Параматмы нет никого иного, кто был бы истинным близким другом."
    },
    {
      "index": 0,
      "verse_id": 18727,
      "shabad_num": 0,
      "shabad_id": null,
      "gurmukhi": "ਮਨਹਿ ਅਰਾਧਿ ਸੋਇ ਹਾਂ ॥",
      "site_roman": "",
      "sahib_singh_pa": "ਸਦਾ ਉਸ (ਪ੍ਰਭੂ) ਨੂੰ ਹੀ ਮਨ ਵਿੱਚ ਸਿਮਰਦਾ ਰਹੁ।",
      "roman": "manah arādh soi hā̃",
      "translation_ru": "Постоянно помни в уме только Его."
    },
    {
      "index": 0,
      "verse_id": 18728,
      "shabad_num": 0,
      "shabad_id": null,
      "gurmukhi": "ਨਿਮਖ ਨ ਵੀਸਰੈ ਹਾਂ ॥",
      "site_roman": "",
      "sahib_singh_pa": "ਉਸ (ਪਰਮਾਤਮਾ ਨੂੰ) ਅੱਖ ਝਮਕਣ ਜਿਤਨੇ ਸਮੇ ਲਈ ਭੀ ਭੁੱਲਣਾ ਨਹੀਂ ਚਾਹੀਦਾ,",
      "roman": "nimakh na vīsrē hā̃",
      "translation_ru": "Его не следует забывать даже на мгновение,"
    },
    {
      "index": 0,
      "verse_id": 18729,
      "shabad_num": 0,
      "shabad_id": null,
      "gurmukhi": "ਤਿਸੁ ਬਿਨੁ ਕਿਉ ਸਰੈ ਹਾਂ ॥",
      "site_roman": "",
      "sahib_singh_pa": "(ਕਿਉਂਕਿ) ਉਸ (ਦੀ ਯਾਦ) ਤੋਂ ਬਿਨਾ ਜੀਵਨ ਸੁਖੀ ਨਹੀਂ ਗੁਜ਼ਰਦਾ।",
      "roman": "tis bin kiu sarē hā̃",
      "translation_ru": "потому что без памяти о Нём жизнь не проходит счастливо."
    },
    {
      "index": 0,
      "verse_id": 18730,
      "shabad_num": 0,
      "shabad_id": null,
      "gurmukhi": "ਗੁਰ ਕਉ ਕੁਰਬਾਨੁ ਜਾਉ ਹਾਂ ॥",
      "site_roman": "",
      "sahib_singh_pa": "ਮੈਂ ਗੁਰੂ ਤੋਂ ਸਦਕੇ ਜਾਂਦਾ ਹਾਂ (ਕਿਉਂਕਿ ਗੁਰੂ ਦੀ ਕਿਰਪਾ ਨਾਲ ਹੀ),",
      "roman": "gur kau kurbān jāu hā̃",
      "translation_ru": "Я жертвую собой ради Гуру, потому что только по милости Гуру"
    },
    {
      "index": 0,
      "verse_id": 18731,
      "shabad_num": 0,
      "shabad_id": null,
      "gurmukhi": "ਨਾਨਕੁ ਜਪੇ ਨਾਉ ਮੇਰੇ ਮਨਾ ॥੨॥੫॥੧੬੧॥",
      "site_roman": "",
      "sahib_singh_pa": "ਹੇ ਨਾਨਕ! ਮੇਰਾ ਮਨ (ਪਰਮਾਤਮਾ ਦਾ) ਨਾਮ ਜਪਦਾ ਹੈ ॥੨॥੫॥੧੬੧॥",
      "roman": "nānak jape nāu mere manā ǁ2ǁ5ǁ161ǁ",
      "translation_ru": "О Нанак! мой ум повторяет Имя Параматмы. ॥2॥5॥161॥"
    },
    {
      "index": 0,
      "verse_id": 18732,
      "shabad_num": 0,
      "shabad_id": null,
      "gurmukhi": "ਆਸਾਵਰੀ ਮਹਲਾ ੫ ॥",
      "site_roman": "",
      "sahib_singh_pa": "None",
      "roman": "āsāvarī mehlā 5",
      "translation_ru": ""
    },
    {
      "index": 0,
      "verse_id": 18733,
      "shabad_num": 0,
      "shabad_id": null,
      "gurmukhi": "ਕਾਰਨ ਕਰਨ ਤੂੰ ਹਾਂ ॥",
      "site_roman": "",
      "sahib_singh_pa": "(ਹੇ ਪ੍ਰਭ!) ਤੂੰ ਸਾਰੇ ਜਗਤ ਦਾ ਰਚਨਹਾਰ ਹੈਂ,",
      "roman": "kāran karan tū̃ hā̃",
      "translation_ru": "О Господь! Ты Творец всего мира,"
    },
    {
      "index": 0,
      "verse_id": 18734,
      "shabad_num": 0,
      "shabad_id": null,
      "gurmukhi": "ਅਵਰੁ ਨਾ ਸੁਝੈ ਮੂੰ ਹਾਂ ॥",
      "site_roman": "",
      "sahib_singh_pa": "ਤੈਥੋਂ ਬਿਨਾ ਮੈਨੂੰ ਕੋਈ ਹੋਰ ਨਹੀਂ ਸੁੱਝਦਾ (ਜੋ ਇਹ ਤਾਕਤ ਰੱਖਦਾ ਹੋਵੇ),",
      "roman": "avar nā sujhē mū̃ hā̃",
      "translation_ru": "кроме Тебя я не вижу никого другого, кто обладал бы такой силой,"
    },
    {
      "index": 0,
      "verse_id": 18735,
      "shabad_num": 0,
      "shabad_id": null,
      "gurmukhi": "ਕਰਹਿ ਸੁ ਹੋਈਐ ਹਾਂ ॥",
      "site_roman": "",
      "sahib_singh_pa": "ਹੇ ਪ੍ਰਭੂ! ਜੋ ਕੁਝ ਤੂੰ ਕਰਦਾ ਹੈਂ ਉਹੀ (ਜਗਤ ਵਿਚ) ਵਰਤਦਾ ਹੈ।",
      "roman": "karah su hoīai hā̃",
      "translation_ru": "О Господь! Всё, что Ты делаешь, то и совершается в мире."
    },
    {
      "index": 0,
      "verse_id": 18736,
      "shabad_num": 0,
      "shabad_id": null,
      "gurmukhi": "ਸਹਜਿ ਸੁਖਿ ਸੋਈਐ ਹਾਂ ॥",
      "site_roman": "",
      "sahib_singh_pa": "ਉਹੀ ਮਨੁਖ ਆਤਮਕ ਅਡੋਲਤਾ ਵਿਚ ਆਨੰਦ ਵਿਚ ਲੀਨ ਰਹਿ ਸਕੀਦਾ ਹੈ,",
      "roman": "sahaj sukh soīai hā̃",
      "translation_ru": "Только тот человек может пребывать, погружённый в радость духовного равновесия,"
    },
    {
      "index": 0,
      "verse_id": 18737,
      "shabad_num": 0,
      "shabad_id": null,
      "gurmukhi": "ਧੀਰਜ ਮਨਿ ਭਏ ਹਾਂ ॥",
      "site_roman": "",
      "sahib_singh_pa": "ਤੇ ਉਸ ਦਾ ਹੀ ਮਨ ਵਿਚ ਹੌਸਲਾ ਬੱਝ ਜਾਂਦਾ ਹੈ,",
      "roman": "dhīraj man bhae hā̃",
      "translation_ru": "и только у него в уме утверждается стойкость,"
    },
    {
      "index": 0,
      "verse_id": 18738,
      "shabad_num": 0,
      "shabad_id": null,
      "gurmukhi": "ਪ੍ਰਭ ਕੈ ਦਰਿ ਪਏ ਮੇਰੇ ਮਨਾ ॥੧॥ ਰਹਾਉ ॥",
      "site_roman": "",
      "sahib_singh_pa": "ਹੇ ਮੇਰੇ ਮਨ! (ਚਤੁਰਾਈਆਂ ਛੱਡ ਕੇ) ਜੋ ਮਨੁਖ ਪਰਮਾਤਮਾ ਦੇ ਦਰ ਤੇ ਡਿੱਗ ਪਵੇ ॥੧॥ ਰਹਾਉ ॥",
      "roman": "prabh kē dar pae mere manā ǁ1ǁ rahāu",
      "translation_ru": "О мой ум! который, оставив хитрости, падает к дверям Параматмы. ॥1॥ Рахау ॥"
    },
    {
      "index": 0,
      "verse_id": 18739,
      "shabad_num": 0,
      "shabad_id": null,
      "gurmukhi": "ਸਾਧੂ ਸੰਗਮੇ ਹਾਂ ॥",
      "site_roman": "",
      "sahib_singh_pa": "(ਹੇ ਮੇਰੇ ਮਨ) ਗੁਰੂ ਦੀ ਸੰਗਤਿ ਵਿਚ ਰਿਹਾਂ,",
      "roman": "sādhū sangme hā̃",
      "translation_ru": "О мой ум! пребывая в обществе Гуру,"
    },
    {
      "index": 0,
      "verse_id": 18740,
      "shabad_num": 0,
      "shabad_id": null,
      "gurmukhi": "ਪੂਰਨ ਸੰਜਮੇ ਹਾਂ ॥",
      "site_roman": "",
      "sahib_singh_pa": "ਉਹ ਜੁਗਤਿ ਪੂਰਨ ਤੌਰ ਤੇ ਆ ਜਾਂਦੀ ਹੈ।",
      "roman": "pūran sanjme hā̃",
      "translation_ru": "человек полностью овладевает этим способом."
    },
    {
      "index": 0,
      "verse_id": 18741,
      "shabad_num": 0,
      "shabad_id": null,
      "gurmukhi": "ਜਬ ਤੇ ਛੁਟੇ ਆਪ ਹਾਂ ॥",
      "site_roman": "",
      "sahib_singh_pa": "(ਹੇ ਮਨ!) ਜਿਸ ਵੇਲੇ (ਮਨੁੱਖ ਦੇ ਅੰਦਰੋਂ) ਹਉਮੈ ਅਹੰਕਾਰ ਮੁੱਕ ਜਾਂਦਾ ਹੈ,",
      "roman": "jab te chhuṭe āp hā̃",
      "translation_ru": "О ум! когда внутри человека исчезает хоумэ, эго,"
    },
    {
      "index": 0,
      "verse_id": 18742,
      "shabad_num": 0,
      "shabad_id": null,
      "gurmukhi": "ਤਬ ਤੇ ਮਿਟੇ ਤਾਪ ਹਾਂ ॥",
      "site_roman": "",
      "sahib_singh_pa": "(ਤੇ ਗੁਰੂ ਦੀ ਓਟ ਠੀਕ ਜਾਪਦੀ ਹੈ) ਉਸੇ ਵੇਲੇ ਤੋਂ (ਮਨ ਦੇ) ਸਾਰੇ ਦੁੱਖ-ਕਲੇਸ਼ ਦੂਰ ਹੋ ਜਾਂਦੇ ਹਨ।",
      "roman": "tab te miṭe tāp hā̃",
      "translation_ru": "с того самого момента, когда опора Гуру становится по-настоящему правильной, уходят все страдания и муки ума."
    },
    {
      "index": 0,
      "verse_id": 18743,
      "shabad_num": 0,
      "shabad_id": null,
      "gurmukhi": "ਕਿਰਪਾ ਧਾਰੀਆ ਹਾਂ ॥",
      "site_roman": "",
      "sahib_singh_pa": "ਹੇ ਜਗਤ ਦੇ ਮਾਲਕ-ਪ੍ਰਭੂ! ਮੇਰੇ ਉੱਤੇ ਮੇਹਰ ਕਰ,",
      "roman": "kirpā dhārīā hā̃",
      "translation_ru": "О Господь, Владыка мира! Яви мне милость,"
    },
    {
      "index": 0,
      "verse_id": 18744,
      "shabad_num": 0,
      "shabad_id": null,
      "gurmukhi": "ਪਤਿ ਰਖੁ ਬਨਵਾਰੀਆ ਮੇਰੇ ਮਨਾ ॥੧॥",
      "site_roman": "",
      "sahib_singh_pa": "ਤੇ ਮੇਰੀ (ਸਰਨ ਪਏ ਦੀ) ਇੱਜ਼ਤ ਰੱਖ ॥੧॥",
      "roman": "pat rakh banvārīā mere manā ǁ1ǁ",
      "translation_ru": "и сохрани мою честь, раз я пришёл в Твоё прибежище. ॥1॥"
    },
    {
      "index": 0,
      "verse_id": 18745,
      "shabad_num": 0,
      "shabad_id": null,
      "gurmukhi": "ਇਹੁ ਸੁਖੁ ਜਾਨੀਐ ਹਾਂ ॥",
      "site_roman": "",
      "sahib_singh_pa": "(ਹੇ ਮੇਰੇ ਮਨ!) ਇਸੇ ਨੂੰ ਹੀ ਸੁਖ (ਦਾ ਮੂਲ) ਸਮਝਣਾ ਚਾਹੀਦਾ ਹੈ,",
      "roman": "ih sukh jānīai hā̃",
      "translation_ru": "О мой ум! Именно это и следует считать подлинным счастьем,"
    },
    {
      "index": 0,
      "verse_id": 18746,
      "shabad_num": 0,
      "shabad_id": null,
      "gurmukhi": "ਹਰਿ ਕਰੇ ਸੁ ਮਾਨੀਐ ਹਾਂ ॥",
      "site_roman": "",
      "sahib_singh_pa": "ਜੋ ਕੁਝ ਪਰਮਾਤਮਾ ਕਰਦਾ ਹੈ ਉਸ ਨੂੰ (ਮਿੱਠਾ ਕਰ ਕੇ) ਮੰਨਣਾ ਚਾਹੀਦਾ ਹੈ,",
      "roman": "har kre su mānīai hā̃",
      "translation_ru": "следует принимать как сладостное всё, что делает Параматма,"
    },
    {
      "index": 0,
      "verse_id": 18747,
      "shabad_num": 0,
      "shabad_id": null,
      "gurmukhi": "ਮੰਦਾ ਨਾਹਿ ਕੋਇ ਹਾਂ ॥",
      "site_roman": "",
      "sahib_singh_pa": "ਹੇ ਮਨ! ਜੇਹੜਾ ਮਨੁੱਖ ਸੰਤ ਜਨਾਂ ਦੇ ਚਰਨਾਂ ਦੀ ਧੂੜ ਬਣਦਾ ਹੈ,",
      "roman": "mandā nāh koi hā̃",
      "translation_ru": "О ум! тот человек, который становится пылью у стоп святых,"
    },
    {
      "index": 0,
      "verse_id": 18748,
      "shabad_num": 0,
      "shabad_id": null,
      "gurmukhi": "ਸੰਤ ਕੀ ਰੇਨ ਹੋਇ ਹਾਂ ॥",
      "site_roman": "",
      "sahib_singh_pa": "ਉਸ ਨੂੰ (ਜਗਤ ਵਿਚ) ਕੋਈ ਭੈੜਾ ਨਹੀਂ ਦਿੱਸਦਾ।",
      "roman": "sant kī ren hoi hā̃",
      "translation_ru": "не видит в мире никого дурным."
    },
    {
      "index": 0,
      "verse_id": 18749,
      "shabad_num": 0,
      "shabad_id": null,
      "gurmukhi": "ਆਪੇ ਜਿਸੁ ਰਖੈ ਹਾਂ ॥",
      "site_roman": "",
      "sahib_singh_pa": "(ਪਰਮਾਤਮਾ) ਆਪ ਹੀ ਜਿਸ ਮਨੁੱਖ ਨੂੰ (ਵਿਕਾਰਾਂ ਵਲੋਂ) ਬਚਾਂਦਾ ਹੈ,",
      "roman": "āpe jis rakhē hā̃",
      "translation_ru": "Того человека, которого Сам Параматма хранит от пороков,"
    },
    {
      "index": 0,
      "verse_id": 18750,
      "shabad_num": 0,
      "shabad_id": null,
      "gurmukhi": "ਹਰਿ ਅੰਮ੍ਰਿਤੁ ਸੋ ਚਖੈ ਮੇਰੇ ਮਨਾ ॥੨॥",
      "site_roman": "",
      "sahib_singh_pa": "ਉਹ ਮਨੁੱਖ ਆਤਮਕ ਜੀਵਨ ਦੇਣ ਵਾਲਾ ਹਰਿ-ਨਾਮ-ਜਲ ਪੀਂਦਾ ਹੈ ॥੨॥",
      "roman": "har amrit so chakhē mere manā ǁ2ǁ",
      "translation_ru": "тот пьёт нектар воды Хари-Имени, дающей духовную жизнь. ॥2॥"
    },
    {
      "index": 0,
      "verse_id": 18751,
      "shabad_num": 0,
      "shabad_id": null,
      "gurmukhi": "ਜਿਸ ਕਾ ਨਾਹਿ ਕੋਇ ਹਾਂ ॥",
      "site_roman": "",
      "sahib_singh_pa": "(ਹੇ ਮੇਰੇ ਮਨ!) ਜਿਸ ਮਨੁੱਖ ਦਾ ਕੋਈ ਭੀ ਸਹਾਈ ਨਹੀਂ ਬਣਦਾ,",
      "roman": "jis kā nāh koi hā̃",
      "translation_ru": "О мой ум! Тот человек, у которого нет никакого помощника,"
    },
    {
      "index": 0,
      "verse_id": 18752,
      "shabad_num": 0,
      "shabad_id": null,
      "gurmukhi": "ਤਿਸ ਕਾ ਪ੍ਰਭੂ ਸੋਇ ਹਾਂ ॥",
      "site_roman": "",
      "sahib_singh_pa": "(ਜੇ ਉਹ ਪ੍ਰਭੂ ਦੀ ਸਰਨ ਆ ਪਏ, ਤਾਂ) ਉਹ ਪ੍ਰਭੂ ਉਸ ਦਾ ਰਾਖਾ ਬਣ ਜਾਂਦਾ ਹੈ।",
      "roman": "tis kā prabhū soi hā̃",
      "translation_ru": "если приходит в прибежище Господа, то этот Господь становится его защитником."
    },
    {
      "index": 0,
      "verse_id": 18753,
      "shabad_num": 0,
      "shabad_id": null,
      "gurmukhi": "ਅੰਤਰਗਤਿ ਬੁਝੈ ਹਾਂ ॥",
      "site_roman": "",
      "sahib_singh_pa": "ਉਹ ਪਰਮਾਤਮਾ ਹਰੇਕ ਦੇ ਦਿਲ ਦੀ ਗੱਲ ਜਾਣ ਲੈਂਦਾ ਹੈ,",
      "roman": "antargat bujhē hā̃",
      "translation_ru": "Этот Параматма знает, что в сердце каждого,"
    },
    {
      "index": 0,
      "verse_id": 18754,
      "shabad_num": 0,
      "shabad_id": null,
      "gurmukhi": "ਸਭੁ ਕਿਛੁ ਤਿਸੁ ਸੁਝੈ ਹਾਂ ॥",
      "site_roman": "",
      "sahib_singh_pa": "ਉਸ ਨੂੰ ਹਰੇਕ ਜੀਵ ਦੀ ਹਰੇਕ ਮਨੋ-ਕਾਮਨਾ ਦੀ ਸਮਝ ਆ ਜਾਂਦੀ ਹੈ।",
      "roman": "sabh kichh tis sujhē hā̃",
      "translation_ru": "Ему понятно всякое желание каждого существа."
    },
    {
      "index": 0,
      "verse_id": 18755,
      "shabad_num": 0,
      "shabad_id": null,
      "gurmukhi": "ਪਤਿਤ ਉਧਾਰਿ ਲੇਹੁ ਹਾਂ ॥",
      "site_roman": "",
      "sahib_singh_pa": "(ਸਾਨੂੰ ਵਿਕਾਰਾਂ ਵਿਚ) ਡਿੱਗੇ ਜੀਵਾਂ ਨੂੰ (ਵਿਕਾਰਾਂ ਤੋਂ) ਬਚਾ ਲੈ!",
      "roman": "patit udhār leh hā̃",
      "translation_ru": "Спаси нас, падших в пороках, от пороков!"
    },
    {
      "index": 0,
      "verse_id": 18756,
      "shabad_num": 0,
      "shabad_id": null,
      "gurmukhi": "ਨਾਨਕ ਅਰਦਾਸਿ ਏਹੁ ਮੇਰੇ ਮਨਾ ॥੩॥੬॥੧੬੨॥",
      "site_roman": "",
      "sahib_singh_pa": "ਹੇ ਨਾਨਕ! ਮੇਰਾ ਮਨ, (ਪਰਮਾਤਮਾ ਦੇ ਦਰ ਤੇ) ਇਉਂ ਅਰਜ਼ੋਈ ਕਰਦਾ ਹੈ ॥੩॥੬॥੧੬੨॥",
      "roman": "nānak ardās eh mere manā ǁ3ǁ6ǁ162ǁ",
      "translation_ru": "О Нанак! Мой ум именно так и возносит мольбу у дверей Параматмы. ॥3॥6॥162॥"
    },
    {
      "index": 0,
      "verse_id": 18757,
      "shabad_num": 0,
      "shabad_id": null,
      "gurmukhi": "ਆਸਾਵਰੀ ਮਹਲਾ ੫ ਇਕਤੁਕਾ ॥",
      "site_roman": "",
      "sahib_singh_pa": "None",
      "roman": "āsāvarī mehlā 5 iktukā",
      "translation_ru": ""
    },
    {
      "index": 0,
      "verse_id": 18758,
      "shabad_num": 0,
      "shabad_id": null,
      "gurmukhi": "ਓਇ ਪਰਦੇਸੀਆ ਹਾਂ ॥",
      "site_roman": "",
      "sahib_singh_pa": "ਜਗਤ ਵਿਚ ਚਾਰ ਦਿਨਾਂ ਲਈ ਆਏ ਹੇ ਜੀਵ!",
      "roman": "oi pardesīā hā̃",
      "translation_ru": "О живое существо, пришедшее в мир на четыре дня!"
    },
    {
      "index": 0,
      "verse_id": 18759,
      "shabad_num": 0,
      "shabad_id": null,
      "gurmukhi": "ਸੁਨਤ ਸੰਦੇਸਿਆ ਹਾਂ ॥੧॥ ਰਹਾਉ ॥",
      "site_roman": "",
      "sahib_singh_pa": "ਇਹ ਸੁਨੇਹਾ ਧਿਆਨ ਨਾਲ ਸੁਣ ॥੧॥ ਰਹਾਉ ॥",
      "roman": "sunat sandesiā hā̃ ǁ1ǁ rahāu",
      "translation_ru": "Внимательно выслушай это послание. ॥1॥ Рахау ॥"
    },
    {
      "index": 0,
      "verse_id": 18760,
      "shabad_num": 0,
      "shabad_id": null,
      "gurmukhi": "ਜਾ ਸਿਉ ਰਚਿ ਰਹੇ ਹਾਂ ॥",
      "site_roman": "",
      "sahib_singh_pa": "(ਤੈਥੋਂ ਪਹਿਲਾਂ ਇਥੇ ਆਏ ਹੋਏ ਜੀਵ) ਜਿਸ ਮਾਇਆ ਦੇ ਮੋਹ ਵਿਚ ਫਸੇ ਰਹੇ,",
      "roman": "jā siu rach rahe hā̃",
      "translation_ru": "Те существа, что пришли сюда до тебя, были запутаны в привязанности к той майе,"
    }
  ]
}
